[{"name":false,"link":"https://www.prothomalo.com/bangladesh/district/%E0%A6%AE%E0%A7%81%E0%A6%A8%E0%A7%8D%E0%A6%B8%E0%A6%BF%E0%A6%97%E0%A6%9E%E0%A7%8D%E0%A6%9C%E0%A7%87-%E0%A6%86-%E0%A6%B2%E0%A7%80%E0%A6%97%E0%A7%87%E0%A6%B0-%E0%A6%AE%E0%A6%A8%E0%A7%8B%E0%A6%A8%E0%A7%9F%E0%A6%A8-%E0%A6%AA%E0%A7%87%E0%A6%B2%E0%A7%87%E0%A6%A8-%E0%A6%A7%E0%A6%B0%E0%A7%8D%E0%A6%B7%E0%A6%A3-%E0%A6%AE%E0%A6%BE%E0%A6%AE%E0%A6%B2%E0%A6%BE%E0%A6%B0-%E0%A6%86%E0%A6%B8%E0%A6%BE%E0%A6%AE%E0%A6%BF","source_name":"Prthom Alo","news_language":"Bangla"},{"name":"চিকিৎসা ছাড়াই এইডস থেকে সেরে উঠলেন ৩০ বছরের নারী","link":"https://www.prothomalo.com/world/%E0%A6%9A%E0%A6%BF%E0%A6%95%E0%A6%BF%E0%A7%8E%E0%A6%B8%E0%A6%BE-%E0%A6%9B%E0%A6%BE%E0%A7%9C%E0%A6%BE%E0%A6%87-%E0%A6%8F%E0%A6%87%E0%A6%A1%E0%A6%B8-%E0%A6%A5%E0%A7%87%E0%A6%95%E0%A7%87-%E0%A6%B8%E0%A7%87%E0%A6%B0%E0%A7%87-%E0%A6%89%E0%A6%A0%E0%A6%B2%E0%A7%87%E0%A6%A8-%E0%A7%A9%E0%A7%A6-%E0%A6%AC%E0%A6%9B%E0%A6%B0%E0%A7%87%E0%A6%B0-%E0%A6%A8%E0%A6%BE%E0%A6%B0%E0%A7%80","source_name":"Prthom Alo","news_language":"Bangla"},{"name":"এবার ‘পিএসজি’ হয়ে বাংলাভিশনকে হারাল প্রথম আলো","link":"https://www.prothomalo.com/sports/football/%E0%A6%8F%E0%A6%AC%E0%A6%BE%E0%A6%B0-%E0%A6%AA%E0%A6%BF%E0%A6%8F%E0%A6%B8%E0%A6%9C%E0%A6%BF-%E0%A6%B9%E0%A7%9F%E0%A7%87-%E0%A6%AC%E0%A6%BE%E0%A6%82%E0%A6%B2%E0%A6%BE%E0%A6%AD%E0%A6%BF%E0%A6%B6%E0%A6%A8%E0%A6%95%E0%A7%87-%E0%A6%B9%E0%A6%BE%E0%A6%B0%E0%A6%BE%E0%A6%B2-%E0%A6%AA%E0%A7%8D%E0%A6%B0%E0%A6%A5%E0%A6%AE-%E0%A6%86%E0%A6%B2%E0%A7%8B","source_name":"Prthom Alo","news_language":"Bangla"},{"name":"বায়ুদূষণ যেভাবে শরীরের বিভিন্ন অঙ্গের ক্ষতি করে","link":"https://www.prothomalo.com/world/india/%E0%A6%AC%E0%A6%BE%E0%A7%9F%E0%A7%81%E0%A6%A6%E0%A7%82%E0%A6%B7%E0%A6%A3-%E0%A6%AF%E0%A7%87%E0%A6%AD%E0%A6%BE%E0%A6%AC%E0%A7%87-%E0%A6%B6%E0%A6%B0%E0%A7%80%E0%A6%B0%E0%A7%87%E0%A6%B0-%E0%A6%AC%E0%A6%BF%E0%A6%AD%E0%A6%BF%E0%A6%A8%E0%A7%8D%E0%A6%A8-%E0%A6%85%E0%A6%99%E0%A7%8D%E0%A6%97%E0%A7%87%E0%A6%B0-%E0%A6%95%E0%A7%8D%E0%A6%B7%E0%A6%A4%E0%A6%BF-%E0%A6%95%E0%A6%B0%E0%A7%87","source_name":"Prthom Alo","news_language":"Bangla"},{"name":"Tajuddin condemns killing of civilians","link":"https://1971.prothomalo.com/media/morning-news/tajuddin-condemns-killing-of-civilians","source_name":"Prthom Alo","news_language":"Bangla"},{"name":"জাহাঙ্গীরের আলাদা মিশন ছিল: আজমত উল্লা খান","link":"https://www.prothomalo.com/politics/%E0%A6%9C%E0%A6%BE%E0%A6%B9%E0%A6%BE%E0%A6%99%E0%A7%8D%E0%A6%97%E0%A7%80%E0%A6%B0%E0%A7%87%E0%A6%B0-%E0%A6%86%E0%A6%B2%E0%A6%BE%E0%A6%A6%E0%A6%BE-%E0%A6%AE%E0%A6%BF%E0%A6%B6%E0%A6%A8-%E0%A6%9B%E0%A6%BF%E0%A6%B2-%E0%A6%86%E0%A6%9C%E0%A6%AE%E0%A6%A4-%E0%A6%89%E0%A6%B2%E0%A7%8D%E0%A6%B2%E0%A6%BE-%E0%A6%96%E0%A6%BE%E0%A6%A8","source_name":"Prthom Alo","news_language":"Bangla"},{"name":"তিন ঘণ্টা পর পাটুরিয়া-দৌলতদিয়া নৌপথে ফেরি চলাচল শুরু","link":"https://www.prothomalo.com/bangladesh/district/%E0%A6%A4%E0%A6%BF%E0%A6%A8-%E0%A6%98%E0%A6%A3%E0%A7%8D%E0%A6%9F%E0%A6%BE-%E0%A6%AA%E0%A6%B0-%E0%A6%AA%E0%A6%BE%E0%A6%9F%E0%A7%81%E0%A6%B0%E0%A6%BF%E0%A7%9F%E0%A6%BE-%E0%A6%A6%E0%A7%8C%E0%A6%B2%E0%A6%A4%E0%A6%A6%E0%A6%BF%E0%A7%9F%E0%A6%BE-%E0%A6%A8%E0%A7%8C%E0%A6%AA%E0%A6%A5%E0%A7%87-%E0%A6%AB%E0%A7%87%E0%A6%B0%E0%A6%BF-%E0%A6%9A%E0%A6%B2%E0%A6%BE%E0%A6%9A%E0%A6%B2-%E0%A6%B6%E0%A7%81%E0%A6%B0%E0%A7%81","source_name":"Prthom Alo","news_language":"Bangla"},{"name":"ঘুমের মধ্যে হাঁটা!","link":"https://www.bigganchinta.com/biology/walking-in-sleep","source_name":"Prthom Alo","news_language":"Bangla"},{"name":"খালেদা জিয়া মৃত্যুর সঙ্গে পাঞ্জা লড়ছেন: রিজভী","link":"https://www.prothomalo.com/politics/%E0%A6%96%E0%A6%BE%E0%A6%B2%E0%A7%87%E0%A6%A6%E0%A6%BE-%E0%A6%9C%E0%A6%BF%E0%A7%9F%E0%A6%BE-%E0%A6%AE%E0%A7%83%E0%A6%A4%E0%A7%8D%E0%A6%AF%E0%A7%81%E0%A6%B0-%E0%A6%B8%E0%A6%99%E0%A7%8D%E0%A6%97%E0%A7%87-%E0%A6%AA%E0%A6%BE%E0%A6%9E%E0%A7%8D%E0%A6%9C%E0%A6%BE-%E0%A6%B2%E0%A7%9C%E0%A6%9B%E0%A7%87%E0%A6%A8-%E0%A6%B0%E0%A6%BF%E0%A6%9C%E0%A6%AD%E0%A7%80","source_name":"Prthom Alo","news_language":"Bangla"},{"name":"Pak Govt. studying Nixon's policy speech","link":"https://1971.prothomalo.com/media/morning-news/pak-govt-studying-nixons-policy-speech","source_name":"Prthom Alo","news_language":"Bangla"},{"name":"বাসাবাড়ির ময়লাও এখন অর্থনীতিতে গুরুত্বপূর্ণ খাত ","link":"https://www.prothomalo.com/business/economics/%E0%A6%AC%E0%A6%BE%E0%A6%B8%E0%A6%BE%E0%A6%AC%E0%A6%BE%E0%A7%9C%E0%A6%BF%E0%A6%B0-%E0%A6%AE%E0%A7%9F%E0%A6%B2%E0%A6%BE%E0%A6%93-%E0%A6%8F%E0%A6%96%E0%A6%A8-%E0%A6%85%E0%A6%B0%E0%A7%8D%E0%A6%A5%E0%A6%A8%E0%A7%80%E0%A6%A4%E0%A6%BF%E0%A6%A4%E0%A7%87-%E0%A6%97%E0%A7%81%E0%A6%B0%E0%A7%81%E0%A6%A4%E0%A7%8D%E0%A6%AC%E0%A6%AA%E0%A7%82%E0%A6%B0%E0%A7%8D%E0%A6%A3-%E0%A6%96%E0%A6%BE%E0%A6%A4","source_name":"Prthom Alo","news_language":"Bangla"},{"name":"Every moment Counts ","link":"https://1971.prothomalo.com/media/morning-news/every-moment-counts","source_name":"Prthom Alo","news_language":"Bangla"},{"name":"বিশ্ব বিজ্ঞান একাডেমির ফেলো হলেন বাংলাদেশি গবেষক","link":"https://www.bigganchinta.com/feature/bangladeshi-researcher-is-a-fellow-of-world-academy-of-sciences","source_name":"Prthom Alo","news_language":"Bangla"},{"name":"calorie নাকি Calorie","link":"https://www.bigganchinta.com/comics/calorie-or-calorie","source_name":"Prthom Alo","news_language":"Bangla"},{"name":"শর্ষে থেকে তেল তৈরি দেখতে গিয়ে প্রাণ হারালেন বৃদ্ধ","link":"https://www.prothomalo.com/bangladesh/district/%E0%A6%B6%E0%A6%B0%E0%A7%8D%E0%A6%B7%E0%A7%87-%E0%A6%A5%E0%A7%87%E0%A6%95%E0%A7%87-%E0%A6%A4%E0%A7%87%E0%A6%B2-%E0%A6%A4%E0%A7%88%E0%A6%B0%E0%A6%BF-%E0%A6%A6%E0%A7%87%E0%A6%96%E0%A6%A4%E0%A7%87-%E0%A6%97%E0%A6%BF%E0%A7%9F%E0%A7%87-%E0%A6%AA%E0%A7%8D%E0%A6%B0%E0%A6%BE%E0%A6%A3-%E0%A6%B9%E0%A6%BE%E0%A6%B0%E0%A6%BE%E0%A6%B2%E0%A7%87%E0%A6%A8-%E0%A6%AC%E0%A7%83%E0%A6%A6%E0%A7%8D%E0%A6%A7","source_name":"Prthom Alo","news_language":"Bangla"},{"name":"ভবিষ্যতে অনেক ব্যাংক একীভূত করতে হবে ","link":"https://www.prothomalo.com/business/bank/%E0%A6%AD%E0%A6%AC%E0%A6%BF%E0%A6%B7%E0%A7%8D%E0%A6%AF%E0%A6%A4%E0%A7%87-%E0%A6%85%E0%A6%A8%E0%A7%87%E0%A6%95-%E0%A6%AC%E0%A7%8D%E0%A6%AF%E0%A6%BE%E0%A6%82%E0%A6%95-%E0%A6%8F%E0%A6%95%E0%A7%80%E0%A6%AD%E0%A7%82%E0%A6%A4-%E0%A6%95%E0%A6%B0%E0%A6%A4%E0%A7%87-%E0%A6%B9%E0%A6%AC%E0%A7%87","source_name":"Prthom Alo","news_language":"Bangla"}]