[{"name":"‘আমার জীবনের অনেকটা জায়গাজুড়ে আছেন তিনি’","link":"https://www.prothomalo.com/entertainment/tv/%E0%A6%86%E0%A6%AE%E0%A6%BE%E0%A6%B0-%E0%A6%9C%E0%A7%80%E0%A6%AC%E0%A6%A8%E0%A7%87%E0%A6%B0-%E0%A6%85%E0%A6%A8%E0%A7%87%E0%A6%95%E0%A6%9F%E0%A6%BE-%E0%A6%9C%E0%A6%BE%E0%A7%9F%E0%A6%97%E0%A6%BE%E0%A6%9C%E0%A7%81%E0%A7%9C%E0%A7%87-%E0%A6%86%E0%A6%9B%E0%A7%87%E0%A6%A8-%E0%A6%A4%E0%A6%BF%E0%A6%A8%E0%A6%BF","source_name":"Prthom Alo","news_language":"Bangla"},{"name":"এপ্রিলের পর এক সপ্তাহে ইউরোপে করোনার রেকর্ড সংক্রমণ ও মৃত্যু: রয়টার্স","link":"https://www.prothomalo.com/world/europe/%E0%A6%8F%E0%A6%AA%E0%A7%8D%E0%A6%B0%E0%A6%BF%E0%A6%B2%E0%A7%87%E0%A6%B0-%E0%A6%AA%E0%A6%B0-%E0%A6%8F%E0%A6%95-%E0%A6%B8%E0%A6%AA%E0%A7%8D%E0%A6%A4%E0%A6%BE%E0%A6%B9%E0%A7%87-%E0%A6%87%E0%A6%89%E0%A6%B0%E0%A7%8B%E0%A6%AA%E0%A7%87-%E0%A6%95%E0%A6%B0%E0%A7%8B%E0%A6%A8%E0%A6%BE%E0%A6%B0-%E0%A6%B0%E0%A7%87%E0%A6%95%E0%A6%B0%E0%A7%8D%E0%A6%A1-%E0%A6%B8%E0%A6%82%E0%A6%95%E0%A7%8D%E0%A6%B0%E0%A6%AE%E0%A6%A3-%E0%A6%93-%E0%A6%AE%E0%A7%83%E0%A6%A4%E0%A7%8D%E0%A6%AF%E0%A7%81-%E0%A6%B0%E0%A7%9F%E0%A6%9F%E0%A6%BE%E0%A6%B0%E0%A7%8D%E0%A6%B8","source_name":"Prthom Alo","news_language":"Bangla"},{"name":"মাহাদিকে কাল আইসিইউ থেকে বের করার সম্ভাবনা","link":"https://www.prothomalo.com/bangladesh/%E0%A6%AE%E0%A6%BE%E0%A6%B9%E0%A6%BE%E0%A6%A6%E0%A6%BF%E0%A6%95%E0%A7%87-%E0%A6%95%E0%A6%BE%E0%A6%B2-%E0%A6%86%E0%A6%87%E0%A6%B8%E0%A6%BF%E0%A6%87%E0%A6%89-%E0%A6%A5%E0%A7%87%E0%A6%95%E0%A7%87-%E0%A6%AC%E0%A7%87%E0%A6%B0-%E0%A6%95%E0%A6%B0%E0%A6%BE%E0%A6%B0-%E0%A6%B8%E0%A6%AE%E0%A7%8D%E0%A6%AD%E0%A6%BE%E0%A6%AC%E0%A6%A8%E0%A6%BE","source_name":"Prthom Alo","news_language":"Bangla"},{"name":false,"link":"https://www.prothomalo.com/bangladesh/capital/%E0%A6%97%E0%A7%81%E0%A6%B2%E0%A6%B6%E0%A6%BE%E0%A6%A8%E0%A7%87-%E0%A6%B8%E0%A7%8D%E0%A6%95%E0%A7%81%E0%A6%B2%E0%A6%9B%E0%A6%BE%E0%A6%A4%E0%A7%8D%E0%A6%B0%E0%A7%80%E0%A6%B0-%E0%A6%B2%E0%A6%BE%E0%A6%B6-%E0%A6%89%E0%A6%A6%E0%A7%8D%E0%A6%A7%E0%A6%BE%E0%A6%B0","source_name":"Prthom Alo","news_language":"Bangla"},{"name":"নূর হোসেনের আত্মা কি আমাদের ক্ষমা করবে","link":"https://www.prothomalo.com/opinion/column/%E0%A6%A8%E0%A7%82%E0%A6%B0-%E0%A6%B9%E0%A7%87%E0%A6%BE%E0%A6%B8%E0%A7%87%E0%A6%A8%E0%A7%87%E0%A6%B0-%E0%A6%86%E0%A6%A4%E0%A7%8D%E0%A6%AE%E0%A6%BE-%E0%A6%95%E0%A6%BF-%E0%A6%86%E0%A6%AE%E0%A6%BE%E0%A6%A6%E0%A7%87%E0%A6%B0-%E0%A6%95%E0%A7%8D%E0%A6%B7%E0%A6%AE%E0%A6%BE-%E0%A6%95%E0%A6%B0%E0%A6%AC%E0%A7%87","source_name":"Prthom Alo","news_language":"Bangla"},{"name":"ভোক্তাশ্রেণির আকার ১০ বছরে দ্বিগুণ হবে","link":"https://www.prothomalo.com/business/economics/%E0%A6%AD%E0%A7%8B%E0%A6%95%E0%A7%8D%E0%A6%A4%E0%A6%BE%E0%A6%B6%E0%A7%8D%E0%A6%B0%E0%A7%87%E0%A6%A3%E0%A6%BF%E0%A6%B0-%E0%A6%86%E0%A6%95%E0%A6%BE%E0%A6%B0-%E0%A7%A7%E0%A7%A6-%E0%A6%AC%E0%A6%9B%E0%A6%B0%E0%A7%87-%E0%A6%A6%E0%A7%8D%E0%A6%AC%E0%A6%BF%E0%A6%97%E0%A7%81%E0%A6%A3-%E0%A6%B9%E0%A6%AC%E0%A7%87","source_name":"Prthom Alo","news_language":"Bangla"},{"name":"তিন ইয়াবা কারখানার সন্ধান ভারত সীমান্তে","link":"https://www.prothomalo.com/bangladesh/crime/%E0%A6%A4%E0%A6%BF%E0%A6%A8-%E0%A6%87%E0%A7%9F%E0%A6%BE%E0%A6%AC%E0%A6%BE-%E0%A6%95%E0%A6%BE%E0%A6%B0%E0%A6%96%E0%A6%BE%E0%A6%A8%E0%A6%BE%E0%A6%B0-%E0%A6%B8%E0%A6%A8%E0%A7%8D%E0%A6%A7%E0%A6%BE%E0%A6%A8-%E0%A6%AD%E0%A6%BE%E0%A6%B0%E0%A6%A4-%E0%A6%B8%E0%A7%80%E0%A6%AE%E0%A6%BE%E0%A6%A8%E0%A7%8D%E0%A6%A4%E0%A7%87","source_name":"Prthom Alo","news_language":"Bangla"},{"name":"রিজওয়ানের দেশপ্রেমে বিস্মিত তাঁকে চিকিৎসা দেওয়া ভারতীয় চিকিৎসক","link":"https://www.prothomalo.com/sports/cricket/%E0%A6%B0%E0%A6%BF%E0%A6%9C%E0%A6%93%E0%A7%9F%E0%A6%BE%E0%A6%A8%E0%A7%87%E0%A6%B0-%E0%A6%A6%E0%A7%87%E0%A6%B6%E0%A6%AA%E0%A7%8D%E0%A6%B0%E0%A7%87%E0%A6%AE%E0%A7%87-%E0%A6%AC%E0%A6%BF%E0%A6%B8%E0%A7%8D%E0%A6%AE%E0%A6%BF%E0%A6%A4-%E0%A6%A4%E0%A6%BE%E0%A6%81%E0%A6%95%E0%A7%87-%E0%A6%9A%E0%A6%BF%E0%A6%95%E0%A6%BF%E0%A7%8E%E0%A6%B8%E0%A6%BE-%E0%A6%A6%E0%A7%87%E0%A6%93%E0%A7%9F%E0%A6%BE-%E0%A6%AD%E0%A6%BE%E0%A6%B0%E0%A6%A4%E0%A7%80%E0%A7%9F-%E0%A6%9A%E0%A6%BF%E0%A6%95%E0%A6%BF%E0%A7%8E%E0%A6%B8%E0%A6%95","source_name":"Prthom Alo","news_language":"Bangla"},{"name":"ফোর্স ","link":"https://1971.prothomalo.com/sector-force/force/%E0%A6%AB%E0%A7%8B%E0%A6%B0%E0%A7%8D%E0%A6%B8","source_name":"Prthom Alo","news_language":"Bangla"},{"name":"শেষ পর্যন্ত জামানত হারালেন আওয়ামী লীগের দুই প্রার্থী ","link":"https://www.prothomalo.com/bangladesh/district/%E0%A6%B6%E0%A7%87%E0%A6%B7-%E0%A6%AA%E0%A6%B0%E0%A7%8D%E0%A6%AF%E0%A6%A8%E0%A7%8D%E0%A6%A4-%E0%A6%9C%E0%A6%BE%E0%A6%AE%E0%A6%BE%E0%A6%A8%E0%A6%A4-%E0%A6%B9%E0%A6%BE%E0%A6%B0%E0%A6%BE%E0%A6%B2%E0%A7%87%E0%A6%A8-%E0%A6%86%E0%A6%93%E0%A7%9F%E0%A6%BE%E0%A6%AE%E0%A7%80-%E0%A6%B2%E0%A7%80%E0%A6%97%E0%A7%87%E0%A6%B0-%E0%A6%A6%E0%A7%81%E0%A6%87-%E0%A6%AA%E0%A7%8D%E0%A6%B0%E0%A6%BE%E0%A6%B0%E0%A7%8D%E0%A6%A5%E0%A7%80","source_name":"Prthom Alo","news_language":"Bangla"},{"name":"Xinc নিবেদিত সুর ও সুরক্ষা | সিজন ৩ | পর্ব ১১","link":"https://www.prothomalo.com/video/xinc-%E0%A6%A8%E0%A6%BF%E0%A6%AC%E0%A7%87%E0%A6%A6%E0%A6%BF%E0%A6%A4-%E0%A6%B8%E0%A7%81%E0%A6%B0-%E0%A6%93-%E0%A6%B8%E0%A7%81%E0%A6%B0%E0%A6%95%E0%A7%8D%E0%A6%B7%E0%A6%BE-%E0%A6%B8%E0%A6%BF%E0%A6%9C%E0%A6%A8-%E0%A7%A9-%E0%A6%AA%E0%A6%B0%E0%A7%8D%E0%A6%AC-%E0%A7%A7%E0%A7%A7","source_name":"Prthom Alo","news_language":"Bangla"},{"name":"আবারও লাভে অ্যাস্ট্রাজেনেকা","link":"https://www.prothomalo.com/world/%E0%A6%86%E0%A6%AC%E0%A6%BE%E0%A6%B0%E0%A6%93-%E0%A6%B2%E0%A6%BE%E0%A6%AD%E0%A7%87-%E0%A6%85%E0%A7%8D%E0%A6%AF%E0%A6%BE%E0%A6%B8%E0%A7%8D%E0%A6%9F%E0%A7%8D%E0%A6%B0%E0%A6%BE%E0%A6%9C%E0%A7%87%E0%A6%A8%E0%A7%87%E0%A6%95%E0%A6%BE","source_name":"Prthom Alo","news_language":"Bangla"},{"name":false,"link":"https://www.prothomalo.com/bangladesh/district/%E0%A6%A8%E0%A6%B0%E0%A6%B8%E0%A6%BF%E0%A6%82%E0%A6%A6%E0%A7%80%E0%A6%A4%E0%A7%87-%E0%A6%86%E0%A6%B2%E0%A7%80%E0%A6%97%E0%A7%87%E0%A6%B0-%E0%A6%A6%E0%A7%81%E0%A6%87-%E0%A6%AC%E0%A6%BF%E0%A6%A6%E0%A7%8D%E0%A6%B0%E0%A7%8B%E0%A6%B9%E0%A7%80-%E0%A6%AA%E0%A7%8D%E0%A6%B0%E0%A6%BE%E0%A6%B0%E0%A7%8D%E0%A6%A5%E0%A7%80%E0%A6%B0-%E0%A6%B8%E0%A6%AE%E0%A6%B0%E0%A7%8D%E0%A6%A5%E0%A6%95%E0%A6%A6%E0%A7%87%E0%A6%B0-%E0%A6%AE%E0%A6%A7%E0%A7%8D%E0%A6%AF%E0%A7%87-%E0%A6%B8%E0%A6%82%E0%A6%98%E0%A6%B0%E0%A7%8D%E0%A6%B7","source_name":"Prthom Alo","news_language":"Bangla"},{"name":"পায়রা উড়ে গেল মাতারবাড়ী","link":"https://www.prothomalo.com/business/industry/%E0%A6%AA%E0%A6%BE%E0%A7%9F%E0%A6%B0%E0%A6%BE-%E0%A6%89%E0%A7%9C%E0%A7%87-%E0%A6%97%E0%A7%87%E0%A6%B2-%E0%A6%AE%E0%A6%BE%E0%A6%A4%E0%A6%BE%E0%A6%B0%E0%A6%AC%E0%A6%BE%E0%A7%9C%E0%A7%80","source_name":"Prthom Alo","news_language":"Bangla"},{"name":"ঢাকা বিশ্ববিদ্যালয় নেবে সায়েন্টিস্ট, বেতন স্কেল ৫০ হাজার","link":"https://www.prothomalo.com/chakri/employment/%E0%A6%A2%E0%A6%BE%E0%A6%95%E0%A6%BE-%E0%A6%AC%E0%A6%BF%E0%A6%B6%E0%A7%8D%E0%A6%AC%E0%A6%AC%E0%A6%BF%E0%A6%A6%E0%A7%8D%E0%A6%AF%E0%A6%BE%E0%A6%B2%E0%A7%9F-%E0%A6%A8%E0%A7%87%E0%A6%AC%E0%A7%87-%E0%A6%B8%E0%A6%BE%E0%A7%9F%E0%A7%87%E0%A6%A8%E0%A7%8D%E0%A6%9F%E0%A6%BF%E0%A6%B8%E0%A7%8D%E0%A6%9F-%E0%A6%AC%E0%A7%87%E0%A6%A4%E0%A6%A8-%E0%A6%B8%E0%A7%8D%E0%A6%95%E0%A7%87%E0%A6%B2-%E0%A7%AB%E0%A7%A6-%E0%A6%B9%E0%A6%BE%E0%A6%9C%E0%A6%BE%E0%A6%B0","source_name":"Prthom Alo","news_language":"Bangla"},{"name":false,"link":"https://www.prothomalo.com/bangladesh/district/%E0%A6%97%E0%A6%BE%E0%A6%9C%E0%A7%80%E0%A6%AA%E0%A7%81%E0%A6%B0%E0%A7%87-%E0%A6%B8%E0%A7%9C%E0%A6%95%E0%A7%87%E0%A6%B0-%E0%A6%AA%E0%A6%BE%E0%A6%B6%E0%A7%87-%E0%A6%AA%E0%A7%9C%E0%A7%87-%E0%A6%9B%E0%A6%BF%E0%A6%B2-%E0%A6%A4%E0%A6%B0%E0%A7%81%E0%A6%A3%E0%A7%87%E0%A6%B0-%E0%A6%B0%E0%A6%95%E0%A7%8D%E0%A6%A4%E0%A6%BE%E0%A6%95%E0%A7%8D%E0%A6%A4-%E0%A6%B2%E0%A6%BE%E0%A6%B6","source_name":"Prthom Alo","news_language":"Bangla"}]