[{"name":"রাজ্যে স্কুল বাস চালকের তীব্র সংকট","link":"https://northamerica.prothomalo.com/new-york/%E0%A6%B0%E0%A6%BE%E0%A6%9C%E0%A7%8D%E0%A6%AF%E0%A7%87-%E0%A6%B8%E0%A7%8D%E0%A6%95%E0%A7%81%E0%A6%B2-%E0%A6%AC%E0%A6%BE%E0%A6%B8-%E0%A6%9A%E0%A6%BE%E0%A6%B2%E0%A6%95%E0%A7%87%E0%A6%B0-%E0%A6%A4%E0%A7%80%E0%A6%AC%E0%A7%8D%E0%A6%B0-%E0%A6%B8%E0%A6%82%E0%A6%95%E0%A6%9F","source_name":"Prthom Alo","news_language":"Bangla"},{"name":"‘পোস্টমাস্টার’ নিয়ে আসছেন সৈয়দ সালাহউদ্দীন জাকী","link":"https://www.prothomalo.com/entertainment/tv/%E0%A6%AA%E0%A7%8B%E0%A6%B8%E0%A7%8D%E0%A6%9F%E0%A6%AE%E0%A6%BE%E0%A6%B8%E0%A7%8D%E0%A6%9F%E0%A6%BE%E0%A6%B0-%E0%A6%A8%E0%A6%BF%E0%A7%9F%E0%A7%87-%E0%A6%86%E0%A6%B8%E0%A6%9B%E0%A7%87%E0%A6%A8-%E0%A6%B8%E0%A7%88%E0%A7%9F%E0%A6%A6-%E0%A6%B8%E0%A6%BE%E0%A6%B2%E0%A6%BE%E0%A6%B9%E0%A6%89%E0%A6%A6%E0%A7%8D%E0%A6%A6%E0%A7%80%E0%A6%A8-%E0%A6%9C%E0%A6%BE%E0%A6%95%E0%A7%80","source_name":"Prthom Alo","news_language":"Bangla"},{"name":"লং আইল্যান্ড সিটিতে নতুন আবাসিক ভবন","link":"https://northamerica.prothomalo.com/new-york/%E0%A6%B2%E0%A6%82-%E0%A6%86%E0%A6%87%E0%A6%B2%E0%A7%8D%E0%A6%AF%E0%A6%BE%E0%A6%A8%E0%A7%8D%E0%A6%A1-%E0%A6%B8%E0%A6%BF%E0%A6%9F%E0%A6%BF%E0%A6%A4%E0%A7%87-%E0%A6%A8%E0%A6%A4%E0%A7%81%E0%A6%A8-%E0%A6%86%E0%A6%AC%E0%A6%BE%E0%A6%B8%E0%A6%BF%E0%A6%95-%E0%A6%AD%E0%A6%AC%E0%A6%A8","source_name":"Prthom Alo","news_language":"Bangla"},{"name":"বিয়ানীবাজার সমিতির নির্বাচন ১০ অক্টোবর ","link":"https://northamerica.prothomalo.com/new-york/%E0%A6%AC%E0%A6%BF%E0%A7%9F%E0%A6%BE%E0%A6%A8%E0%A7%80%E0%A6%AC%E0%A6%BE%E0%A6%9C%E0%A6%BE%E0%A6%B0-%E0%A6%B8%E0%A6%AE%E0%A6%BF%E0%A6%A4%E0%A6%BF%E0%A6%B0-%E0%A6%A8%E0%A6%BF%E0%A6%B0%E0%A7%8D%E0%A6%AC%E0%A6%BE%E0%A6%9A%E0%A6%A8-%E0%A7%A7%E0%A7%A6-%E0%A6%85%E0%A6%95%E0%A7%8D%E0%A6%9F%E0%A7%8B%E0%A6%AC%E0%A6%B0","source_name":"Prthom Alo","news_language":"Bangla"},{"name":"উপজেলা পরিষদ জটিলতার অবসান চাই","link":"https://www.prothomalo.com/opinion/column/%E0%A6%89%E0%A6%AA%E0%A6%9C%E0%A7%87%E0%A6%B2%E0%A6%BE-%E0%A6%AA%E0%A6%B0%E0%A6%BF%E0%A6%B7%E0%A6%A6-%E0%A6%9C%E0%A6%9F%E0%A6%BF%E0%A6%B2%E0%A6%A4%E0%A6%BE%E0%A6%B0-%E0%A6%85%E0%A6%AC%E0%A6%B8%E0%A6%BE%E0%A6%A8-%E0%A6%9A%E0%A6%BE%E0%A6%87-2","source_name":"Prthom Alo","news_language":"Bangla"},{"name":"ভক্তদের জন্য ইনডালোর সারপ্রাইজ গান","link":"https://www.prothomalo.com/entertainment/song/%E0%A6%AD%E0%A6%95%E0%A7%8D%E0%A6%A4%E0%A6%A6%E0%A7%87%E0%A6%B0-%E0%A6%9C%E0%A6%A8%E0%A7%8D%E0%A6%AF-%E0%A6%87%E0%A6%A8%E0%A6%A1%E0%A6%BE%E0%A6%B2%E0%A7%8B%E0%A6%B0-%E0%A6%B8%E0%A6%BE%E0%A6%B0%E0%A6%AA%E0%A7%8D%E0%A6%B0%E0%A6%BE%E0%A6%87%E0%A6%9C-%E0%A6%97%E0%A6%BE%E0%A6%A8","source_name":"Prthom Alo","news_language":"Bangla"},{"name":"ভোটাধিকার পুনরুদ্ধারের জন্য প্রস্তুত হচ্ছে বিএনপি","link":"https://www.prothomalo.com/bangladesh/district/%E0%A6%AD%E0%A7%8B%E0%A6%9F%E0%A6%BE%E0%A6%A7%E0%A6%BF%E0%A6%95%E0%A6%BE%E0%A6%B0-%E0%A6%AA%E0%A7%81%E0%A6%A8%E0%A6%B0%E0%A7%81%E0%A6%A6%E0%A7%8D%E0%A6%A7%E0%A6%BE%E0%A6%B0%E0%A7%87%E0%A6%B0-%E0%A6%9C%E0%A6%A8%E0%A7%8D%E0%A6%AF-%E0%A6%AA%E0%A7%8D%E0%A6%B0%E0%A6%B8%E0%A7%8D%E0%A6%A4%E0%A7%81%E0%A6%A4-%E0%A6%B9%E0%A6%9A%E0%A7%8D%E0%A6%9B%E0%A7%87-%E0%A6%AC%E0%A6%BF%E0%A6%8F%E0%A6%A8%E0%A6%AA%E0%A6%BF","source_name":"Prthom Alo","news_language":"Bangla"},{"name":"৭০ বছর পর বাবার কবর জিয়ারত আবদুল কুদ্দুসের","link":"https://www.prothomalo.com/bangladesh/district/%E0%A7%AD%E0%A7%A6-%E0%A6%AC%E0%A6%9B%E0%A6%B0-%E0%A6%AA%E0%A6%B0-%E0%A6%AC%E0%A6%BE%E0%A6%AC%E0%A6%BE%E0%A6%B0-%E0%A6%95%E0%A6%AC%E0%A6%B0-%E0%A6%9C%E0%A6%BF%E0%A7%9F%E0%A6%BE%E0%A6%B0%E0%A6%A4-%E0%A6%86%E0%A6%AC%E0%A6%A6%E0%A7%81%E0%A6%B2-%E0%A6%95%E0%A7%81%E0%A6%A6%E0%A7%8D%E0%A6%A6%E0%A7%81%E0%A6%B8%E0%A7%87%E0%A6%B0","source_name":"Prthom Alo","news_language":"Bangla"},{"name":"ব্রঙ্কস কমিউনিটি বোর্ডের সদস্য হলেন জুয়েল ","link":"https://northamerica.prothomalo.com/new-york/%E0%A6%AC%E0%A7%8D%E0%A6%B0%E0%A6%99%E0%A7%8D%E0%A6%95%E0%A6%B8-%E0%A6%95%E0%A6%AE%E0%A6%BF%E0%A6%89%E0%A6%A8%E0%A6%BF%E0%A6%9F%E0%A6%BF-%E0%A6%AC%E0%A7%8B%E0%A6%B0%E0%A7%8D%E0%A6%A1%E0%A7%87%E0%A6%B0-%E0%A6%B8%E0%A6%A6%E0%A6%B8%E0%A7%8D%E0%A6%AF-%E0%A6%B9%E0%A6%B2%E0%A7%87%E0%A6%A8-%E0%A6%9C%E0%A7%81%E0%A7%9F%E0%A7%87%E0%A6%B2","source_name":"Prthom Alo","news_language":"Bangla"},{"name":"৩২২ দিন পর ফেরা গোলে রাঙালেন বার্সার নতুন ‘১০’","link":"https://www.prothomalo.com/sports/football/%E0%A7%A9%E0%A7%A8%E0%A7%A8-%E0%A6%A6%E0%A6%BF%E0%A6%A8-%E0%A6%AA%E0%A6%B0-%E0%A6%AB%E0%A7%87%E0%A6%B0%E0%A6%BE-%E0%A6%97%E0%A7%8B%E0%A6%B2%E0%A7%87-%E0%A6%B0%E0%A6%BE%E0%A6%99%E0%A6%BE%E0%A6%B2%E0%A7%87%E0%A6%A8-%E0%A6%AC%E0%A6%BE%E0%A6%B0%E0%A7%8D%E0%A6%B8%E0%A6%BE%E0%A6%B0-%E0%A6%A8%E0%A6%A4%E0%A7%81%E0%A6%A8-%E0%A7%A7%E0%A7%A6","source_name":"Prthom Alo","news_language":"Bangla"},{"name":"পাসপোর্ট–জাতীয় পরিচয়পত্র বদলে ফেলছে তালেবান","link":"https://www.prothomalo.com/world/asia/%E0%A6%AA%E0%A6%BE%E0%A6%B8%E0%A6%AA%E0%A7%8B%E0%A6%B0%E0%A7%8D%E0%A6%9F%E0%A6%9C%E0%A6%BE%E0%A6%A4%E0%A7%80%E0%A7%9F-%E0%A6%AA%E0%A6%B0%E0%A6%BF%E0%A6%9A%E0%A7%9F%E0%A6%AA%E0%A6%A4%E0%A7%8D%E0%A6%B0-%E0%A6%AC%E0%A6%A6%E0%A6%B2%E0%A7%87-%E0%A6%AB%E0%A7%87%E0%A6%B2%E0%A6%9B%E0%A7%87-%E0%A6%A4%E0%A6%BE%E0%A6%B2%E0%A7%87%E0%A6%AC%E0%A6%BE%E0%A6%A8","source_name":"Prthom Alo","news_language":"Bangla"},{"name":"বাংলাদেশের বিদায়ী কোচদেরই পছন্দ হচ্ছে ইস্ট বেঙ্গলের","link":"https://www.prothomalo.com/sports/football/%E0%A6%AC%E0%A6%BE%E0%A6%82%E0%A6%B2%E0%A6%BE%E0%A6%A6%E0%A7%87%E0%A6%B6%E0%A7%87%E0%A6%B0-%E0%A6%AC%E0%A6%BF%E0%A6%A6%E0%A6%BE%E0%A7%9F%E0%A7%80-%E0%A6%95%E0%A7%8B%E0%A6%9A%E0%A6%A6%E0%A7%87%E0%A6%B0%E0%A6%87-%E0%A6%AA%E0%A6%9B%E0%A6%A8%E0%A7%8D%E0%A6%A6-%E0%A6%B9%E0%A6%9A%E0%A7%8D%E0%A6%9B%E0%A7%87-%E0%A6%87%E0%A6%B8%E0%A7%8D%E0%A6%9F-%E0%A6%AC%E0%A7%87%E0%A6%99%E0%A7%8D%E0%A6%97%E0%A6%B2%E0%A7%87%E0%A6%B0","source_name":"Prthom Alo","news_language":"Bangla"},{"name":"মার্কিন হুঁশিয়ারির তোয়াক্কা না করে রুশ ক্ষেপণাস্ত্র ব্যবস্থা কিনতে চায় তুরস্ক","link":"https://www.prothomalo.com/world/europe/%E0%A6%AE%E0%A6%BE%E0%A6%B0%E0%A7%8D%E0%A6%95%E0%A6%BF%E0%A6%A8-%E0%A6%B9%E0%A7%81%E0%A6%81%E0%A6%B6%E0%A6%BF%E0%A7%9F%E0%A6%BE%E0%A6%B0%E0%A6%BF%E0%A6%B0-%E0%A6%A4%E0%A7%8B%E0%A7%9F%E0%A6%BE%E0%A6%95%E0%A7%8D%E0%A6%95%E0%A6%BE-%E0%A6%A8%E0%A6%BE-%E0%A6%95%E0%A6%B0%E0%A7%87-%E0%A6%B0%E0%A7%81%E0%A6%B6-%E0%A6%95%E0%A7%8D%E0%A6%B7%E0%A7%87%E0%A6%AA%E0%A6%A3%E0%A6%BE%E0%A6%B8%E0%A7%8D%E0%A6%A4%E0%A7%8D%E0%A6%B0-%E0%A6%AC%E0%A7%8D%E0%A6%AF%E0%A6%AC%E0%A6%B8%E0%A7%8D%E0%A6%A5%E0%A6%BE-%E0%A6%95%E0%A6%BF%E0%A6%A8%E0%A6%A4%E0%A7%87-%E0%A6%9A%E0%A6%BE%E0%A7%9F-%E0%A6%A4%E0%A7%81%E0%A6%B0%E0%A6%B8%E0%A7%8D%E0%A6%95","source_name":"Prthom Alo","news_language":"Bangla"},{"name":"পিউটার হবে কম কম নট বেশি বেশি","link":"https://www.kishoralo.com/feature/%E0%A6%AA%E0%A6%BF%E0%A6%89%E0%A6%9F%E0%A6%BE%E0%A6%B0-%E0%A6%B9%E0%A6%AC%E0%A7%87-%E0%A6%95%E0%A6%AE-%E0%A6%95%E0%A6%AE-%E0%A6%A8%E0%A6%9F-%E0%A6%AC%E0%A7%87%E0%A6%B6%E0%A6%BF-%E0%A6%AC%E0%A7%87%E0%A6%B6%E0%A6%BF","source_name":"Prthom Alo","news_language":"Bangla"},{"name":"অপরিকল্পিত গর্ভধারণ আর নয়","link":"https://www.prothomalo.com/video/%E0%A6%85%E0%A6%AA%E0%A6%B0%E0%A6%BF%E0%A6%95%E0%A6%B2%E0%A7%8D%E0%A6%AA%E0%A6%BF%E0%A6%A4-%E0%A6%97%E0%A6%B0%E0%A7%8D%E0%A6%AD%E0%A6%A7%E0%A6%BE%E0%A6%B0%E0%A6%A3-%E0%A6%86%E0%A6%B0-%E0%A6%A8%E0%A7%9F","source_name":"Prthom Alo","news_language":"Bangla"},{"name":false,"link":"https://www.prothomalo.com/bangladesh/district/%E0%A6%97%E0%A7%8D%E0%A6%B0%E0%A7%87%E0%A6%AA%E0%A7%8D%E0%A6%A4%E0%A6%BE%E0%A6%B0-%E0%A6%AA%E0%A6%BE%E0%A6%B0%E0%A7%8D%E0%A6%A5%E0%A6%B0-%E0%A6%AB%E0%A6%BE%E0%A6%81%E0%A6%B8%E0%A6%BF%E0%A6%B0-%E0%A6%A6%E0%A6%BE%E0%A6%AC%E0%A6%BF%E0%A6%A4%E0%A7%87-%E0%A6%B8%E0%A6%BE%E0%A6%A4%E0%A6%95%E0%A7%8D%E0%A6%B7%E0%A7%80%E0%A6%B0%E0%A6%BE%E0%A7%9F-%E0%A6%AE%E0%A6%BE%E0%A6%A8%E0%A6%AC%E0%A6%AC%E0%A6%A8%E0%A7%8D%E0%A6%A7%E0%A6%A8","source_name":"Prthom Alo","news_language":"Bangla"}]