[{"name":false,"link":"https://www.prothomalo.com/bangladesh/coronavirus/%E0%A6%95%E0%A6%B0%E0%A7%8B%E0%A6%A8%E0%A6%BE%E0%A7%9F-%E0%A6%AE%E0%A7%83%E0%A6%A4%E0%A7%8D%E0%A6%AF%E0%A7%81-%E0%A6%95%E0%A6%AE%E0%A6%B2%E0%A7%87%E0%A6%93-%E0%A6%B6%E0%A6%A8%E0%A6%BE%E0%A6%95%E0%A7%8D%E0%A6%A4-%E0%A6%AC%E0%A7%87%E0%A7%9C%E0%A7%87%E0%A6%9B%E0%A7%87-3","source_name":"Prthom Alo","news_language":"Bangla"},{"name":"৬ মাস বাংলাদেশের হয়ে টি-টোয়েন্টি খেলবেন না তামিম ","link":"https://www.prothomalo.com/sports/cricket/%E0%A7%AC-%E0%A6%AE%E0%A6%BE%E0%A6%B8-%E0%A6%AC%E0%A6%BE%E0%A6%82%E0%A6%B2%E0%A6%BE%E0%A6%A6%E0%A7%87%E0%A6%B6%E0%A7%87%E0%A6%B0-%E0%A6%B9%E0%A7%9F%E0%A7%87-%E0%A6%9F%E0%A6%BF-%E0%A6%9F%E0%A7%8B%E0%A7%9F%E0%A7%87%E0%A6%A8%E0%A7%8D%E0%A6%9F%E0%A6%BF-%E0%A6%96%E0%A7%87%E0%A6%B2%E0%A6%AC%E0%A7%87%E0%A6%A8-%E0%A6%A8%E0%A6%BE-%E0%A6%A4%E0%A6%BE%E0%A6%AE%E0%A6%BF%E0%A6%AE","source_name":"Prthom Alo","news_language":"Bangla"},{"name":false,"link":"https://www.prothomalo.com/bangladesh/%E0%A6%B0%E0%A7%8D%E0%A6%AF%E0%A6%BE%E0%A6%AC%E0%A7%87%E0%A6%B0-%E0%A6%AC%E0%A6%BF%E0%A6%B0%E0%A7%81%E0%A6%A6%E0%A7%8D%E0%A6%A7%E0%A7%87-%E0%A6%9A%E0%A6%BF%E0%A6%A0%E0%A6%BF-%E0%A6%AC%E0%A6%BE%E0%A6%82%E0%A6%B2%E0%A6%BE%E0%A6%A6%E0%A7%87%E0%A6%B6%E0%A7%87%E0%A6%B0-%E0%A6%B8%E0%A6%99%E0%A7%8D%E0%A6%97%E0%A7%87-%E0%A6%AC%E0%A6%BE%E0%A6%A3%E0%A6%BF%E0%A6%9C%E0%A7%8D%E0%A6%AF%E0%A7%87-%E0%A6%AA%E0%A7%8D%E0%A6%B0%E0%A6%AD%E0%A6%BE%E0%A6%AC-%E0%A6%AB%E0%A7%87%E0%A6%B2%E0%A6%AC%E0%A7%87-%E0%A6%A8%E0%A6%BE-%E0%A6%87%E0%A6%87%E0%A6%89%E0%A6%B0-%E0%A6%B0%E0%A6%BE%E0%A6%B7%E0%A7%8D%E0%A6%9F%E0%A7%8D%E0%A6%B0%E0%A6%A6%E0%A7%82%E0%A6%A4","source_name":"Prthom Alo","news_language":"Bangla"},{"name":"আসছে বুবলী-সিয়ামের ‘টান’","link":"https://www.prothomalo.com/video/bangladesh/%E0%A6%86%E0%A6%B8%E0%A6%9B%E0%A7%87-%E0%A6%AC%E0%A7%81%E0%A6%AC%E0%A6%B2%E0%A7%80-%E0%A6%B8%E0%A6%BF%E0%A6%AF%E0%A6%BC%E0%A6%BE%E0%A6%AE%E0%A7%87%E0%A6%B0-%E0%A6%9F%E0%A6%BE%E0%A6%A8-2","source_name":"Prthom Alo","news_language":"Bangla"},{"name":"এসএসসি ২০২২ - জীববিজ্ঞান | অধ্যায় ১ : বহুনির্বাচনি প্রশ্ন","link":"https://www.prothomalo.com/education/%E0%A6%8F%E0%A6%B8%E0%A6%8F%E0%A6%B8%E0%A6%B8%E0%A6%BF-%E0%A7%A8%E0%A7%A6%E0%A7%A8%E0%A7%A8-%E0%A6%9C%E0%A7%80%E0%A6%AC%E0%A6%AC%E0%A6%BF%E0%A6%9C%E0%A7%8D%E0%A6%9E%E0%A6%BE%E0%A6%A8-%E0%A6%85%E0%A6%A7%E0%A7%8D%E0%A6%AF%E0%A6%BE%E0%A7%9F-%E0%A7%A7-%E0%A6%AC%E0%A6%B9%E0%A7%81%E0%A6%A8%E0%A6%BF%E0%A6%B0%E0%A7%8D%E0%A6%AC%E0%A6%BE%E0%A6%9A%E0%A6%A8%E0%A6%BF-%E0%A6%AA%E0%A7%8D%E0%A6%B0%E0%A6%B6%E0%A7%8D%E0%A6%A8-%E0%A7%A8%E0%A7%A7-%E0%A7%A9%E0%A7%A6","source_name":"Prthom Alo","news_language":"Bangla"},{"name":"এসএসসি ২০২২ - ইংরেজি ২য় পত্র | Fill In The Blanks","link":"https://www.prothomalo.com/education/%E0%A6%8F%E0%A6%B8%E0%A6%8F%E0%A6%B8%E0%A6%B8%E0%A6%BF-%E0%A7%A8%E0%A7%A6%E0%A7%A8%E0%A7%A8%E0%A6%87%E0%A6%82%E0%A6%B0%E0%A7%87%E0%A6%9C%E0%A6%BF-%E0%A7%A8%E0%A7%9F-%E0%A6%AA%E0%A6%A4%E0%A7%8D%E0%A6%B0-fill-in-the-blanks-1","source_name":"Prthom Alo","news_language":"Bangla"},{"name":"এইচএসসি ২০২২ - ভূগোল ১ম পত্র | অধ্যায় ২ : সৃজনশীল প্রশ্ন","link":"https://www.prothomalo.com/education/%E0%A6%8F%E0%A6%87%E0%A6%9A%E0%A6%8F%E0%A6%B8%E0%A6%B8%E0%A6%BF-%E0%A7%A8%E0%A7%A6%E0%A7%A8%E0%A7%A8-%E0%A6%AD%E0%A7%82%E0%A6%97%E0%A7%8B%E0%A6%B2-%E0%A7%A7%E0%A6%AE-%E0%A6%AA%E0%A6%A4%E0%A7%8D%E0%A6%B0-%E0%A6%85%E0%A6%A7%E0%A7%8D%E0%A6%AF%E0%A6%BE%E0%A7%9F-%E0%A7%A8-%E0%A6%B8%E0%A7%83%E0%A6%9C%E0%A6%A8%E0%A6%B6%E0%A7%80%E0%A6%B2-%E0%A6%AA%E0%A7%8D%E0%A6%B0%E0%A6%B6%E0%A7%8D%E0%A6%A8-%E0%A6%85%E0%A6%A7%E0%A7%8D%E0%A6%AF%E0%A6%BE%E0%A7%9F-%E0%A7%A8-%E0%A7%AA","source_name":"Prthom Alo","news_language":"Bangla"},{"name":"দশম শ্রেণি - বাংলা ১ম পত্র | শিক্ষা ও মনুষ্যত্ব : বহুনির্বাচনি প্রশ্ন","link":"https://www.prothomalo.com/education/%E0%A6%A6%E0%A6%B6%E0%A6%AE-%E0%A6%B6%E0%A7%8D%E0%A6%B0%E0%A7%87%E0%A6%A3%E0%A6%BF-%E0%A6%AC%E0%A6%BE%E0%A6%82%E0%A6%B2%E0%A6%BE-%E0%A7%A7%E0%A6%AE-%E0%A6%B6%E0%A6%BF%E0%A6%95%E0%A7%8D%E0%A6%B7%E0%A6%BE-%E0%A6%93-%E0%A6%AE%E0%A6%A8%E0%A7%81%E0%A6%B7%E0%A7%8D%E0%A6%AF%E0%A6%A4%E0%A7%8D%E0%A6%AC-%E0%A6%AC%E0%A6%B9%E0%A7%81%E0%A6%A8%E0%A6%BF%E0%A6%B0%E0%A7%8D%E0%A6%AC%E0%A6%BE%E0%A6%9A%E0%A6%A8%E0%A6%BF-%E0%A6%AA%E0%A7%8D%E0%A6%B0%E0%A6%B6%E0%A7%8D%E0%A6%A8-%E0%A7%A7-%E0%A7%A7%E0%A7%A6","source_name":"Prthom Alo","news_language":"Bangla"},{"name":"নবম শ্রেণি - বাংলা ২য় পত্র । সমাস : বহুনির্বাচনি প্রশ্ন","link":"https://www.prothomalo.com/education/%E0%A6%A8%E0%A6%AC%E0%A6%AE-%E0%A6%B6%E0%A7%8D%E0%A6%B0%E0%A7%87%E0%A6%A3%E0%A6%BF-%E0%A6%AC%E0%A6%BE%E0%A6%82%E0%A6%B2%E0%A6%BE-%E0%A7%A8%E0%A7%9F-%E0%A6%AA%E0%A6%A4%E0%A7%8D%E0%A6%B0-%E0%A6%B8%E0%A6%AE%E0%A6%BE%E0%A6%B8-%E0%A6%AC%E0%A6%B9%E0%A7%81%E0%A6%A8%E0%A6%BF%E0%A6%B0%E0%A7%8D%E0%A6%AC%E0%A6%BE%E0%A6%9A%E0%A6%A8%E0%A6%BF-%E0%A6%AA%E0%A7%8D%E0%A6%B0%E0%A6%B6%E0%A7%8D%E0%A6%A8-%E0%A7%A9%E0%A7%A7-%E0%A7%AA%E0%A7%A6","source_name":"Prthom Alo","news_language":"Bangla"},{"name":"অষ্টম শ্রেণি – বাংলা | তৈলচিত্রের ভূত: বহুনির্বাচনি প্রশ্ন","link":"https://www.prothomalo.com/education/%E0%A6%85%E0%A6%B7%E0%A7%8D%E0%A6%9F%E0%A6%AE-%E0%A6%B6%E0%A7%8D%E0%A6%B0%E0%A7%87%E0%A6%A3%E0%A6%BF%E0%A6%AC%E0%A6%BE%E0%A6%82%E0%A6%B2%E0%A6%BE-%E0%A6%A4%E0%A7%88%E0%A6%B2%E0%A6%9A%E0%A6%BF%E0%A6%A4%E0%A7%8D%E0%A6%B0%E0%A7%87%E0%A6%B0-%E0%A6%AD%E0%A7%82%E0%A6%A4-%E0%A6%AC%E0%A6%B9%E0%A7%81%E0%A6%A8%E0%A6%BF%E0%A6%B0%E0%A7%8D%E0%A6%AC%E0%A6%BE%E0%A6%9A%E0%A6%A8%E0%A6%BF-%E0%A6%AA%E0%A7%8D%E0%A6%B0%E0%A6%B6%E0%A7%8D%E0%A6%A8-%E0%A7%A7%E0%A7%A7-%E0%A7%A8%E0%A7%A6","source_name":"Prthom Alo","news_language":"Bangla"},{"name":"ব্যর্থতার দায় সব শিক্ষককে নিতে হবে","link":"https://www.prothomalo.com/opinion/interview/%E0%A6%AC%E0%A7%8D%E0%A6%AF%E0%A6%B0%E0%A7%8D%E0%A6%A5%E0%A6%A4%E0%A6%BE%E0%A6%B0-%E0%A6%A6%E0%A6%BE%E0%A7%9F-%E0%A6%B8%E0%A6%AC-%E0%A6%B6%E0%A6%BF%E0%A6%95%E0%A7%8D%E0%A6%B7%E0%A6%95%E0%A6%95%E0%A7%87-%E0%A6%A8%E0%A6%BF%E0%A6%A4%E0%A7%87-%E0%A6%B9%E0%A6%AC%E0%A7%87","source_name":"Prthom Alo","news_language":"Bangla"},{"name":"বিপন্ন চন্দনা টিয়া","link":"https://www.bigganchinta.com/biology/endangered-alexandrine-parakeet","source_name":"Prthom Alo","news_language":"Bangla"},{"name":"ছয় বছরে ৩৮ দিন ভালো বায়ু পেয়েছে রাজধানীবাসী","link":"https://www.prothomalo.com/bangladesh/environment/%E0%A6%9B%E0%A6%AF%E0%A6%BC-%E0%A6%AC%E0%A6%9B%E0%A6%B0%E0%A7%87-%E0%A7%A9%E0%A7%AE-%E0%A6%A6%E0%A6%BF%E0%A6%A8-%E0%A6%AD%E0%A6%BE%E0%A6%B2%E0%A7%8B-%E0%A6%AC%E0%A6%BE%E0%A7%9F%E0%A7%81-%E0%A6%AA%E0%A7%87%E0%A7%9F%E0%A7%87%E0%A6%9B%E0%A7%87-%E0%A6%B0%E0%A6%BE%E0%A6%9C%E0%A6%A7%E0%A6%BE%E0%A6%A8%E0%A7%80%E0%A6%AC%E0%A6%BE%E0%A6%B8%E0%A7%80","source_name":"Prthom Alo","news_language":"Bangla"},{"name":"দৌলতখানে অবসরপ্রাপ্ত সেনাসদস্যকে পিটিয়ে হত্যার অভিযোগ","link":"https://www.prothomalo.com/bangladesh/district/%E0%A6%A6%E0%A7%8C%E0%A6%B2%E0%A6%A4%E0%A6%96%E0%A6%BE%E0%A6%A8%E0%A7%87-%E0%A6%85%E0%A6%AC%E0%A6%B8%E0%A6%B0%E0%A6%AA%E0%A7%8D%E0%A6%B0%E0%A6%BE%E0%A6%AA%E0%A7%8D%E0%A6%A4-%E0%A6%B8%E0%A7%87%E0%A6%A8%E0%A6%BE%E0%A6%B8%E0%A6%A6%E0%A6%B8%E0%A7%8D%E0%A6%AF%E0%A6%95%E0%A7%87-%E0%A6%AA%E0%A6%BF%E0%A6%9F%E0%A6%BF%E0%A7%9F%E0%A7%87-%E0%A6%B9%E0%A6%A4%E0%A7%8D%E0%A6%AF%E0%A6%BE%E0%A6%B0-%E0%A6%85%E0%A6%AD%E0%A6%BF%E0%A6%AF%E0%A7%8B%E0%A6%97","source_name":"Prthom Alo","news_language":"Bangla"},{"name":"মেট্রোরেলের পুরো কাঠামো দৃশ্যমান","link":"https://www.prothomalo.com/bangladesh/capital/%E0%A6%AE%E0%A7%87%E0%A6%9F%E0%A7%8D%E0%A6%B0%E0%A7%8B%E0%A6%B0%E0%A7%87%E0%A6%B2%E0%A7%87%E0%A6%B0-%E0%A6%AA%E0%A7%81%E0%A6%B0%E0%A7%8B-%E0%A6%95%E0%A6%BE%E0%A6%A0%E0%A6%BE%E0%A6%AE%E0%A7%8B-%E0%A6%A6%E0%A7%83%E0%A6%B6%E0%A7%8D%E0%A6%AF%E0%A6%AE%E0%A6%BE%E0%A6%A8","source_name":"Prthom Alo","news_language":"Bangla"},{"name":"ছেলের চোখের আলো ফেরাতে বাবা এখন নিঃস্বপ্রায়","link":"https://www.prothomalo.com/bangladesh/%E0%A6%9B%E0%A7%87%E0%A6%B2%E0%A7%87%E0%A6%B0-%E0%A6%9A%E0%A7%8B%E0%A6%96%E0%A7%87%E0%A6%B0-%E0%A6%86%E0%A6%B2%E0%A7%8B-%E0%A6%AB%E0%A7%87%E0%A6%B0%E0%A6%BE%E0%A6%A4%E0%A7%87-%E0%A6%AC%E0%A6%BE%E0%A6%AC%E0%A6%BE-%E0%A6%8F%E0%A6%96%E0%A6%A8-%E0%A6%A8%E0%A6%BF%E0%A6%83%E0%A6%B8%E0%A7%8D%E0%A6%AC%E0%A6%AA%E0%A7%8D%E0%A6%B0%E0%A6%BE%E0%A7%9F","source_name":"Prthom Alo","news_language":"Bangla"}]