[{"name":"নিউইয়র্ক সিটি কাউন্সিলে জিতে ইতিহাস বাংলাদেশি শাহানার","link":"https://www.prothomalo.com/world/usa/%E0%A6%A8%E0%A6%BF%E0%A6%89%E0%A6%87%E0%A7%9F%E0%A6%B0%E0%A7%8D%E0%A6%95-%E0%A6%B8%E0%A6%BF%E0%A6%9F%E0%A6%BF-%E0%A6%95%E0%A6%BE%E0%A6%89%E0%A6%A8%E0%A7%8D%E0%A6%B8%E0%A6%BF%E0%A6%B2%E0%A7%87-%E0%A6%9C%E0%A6%BF%E0%A6%A4%E0%A7%87-%E0%A6%87%E0%A6%A4%E0%A6%BF%E0%A6%B9%E0%A6%BE%E0%A6%B8-%E0%A6%AC%E0%A6%BE%E0%A6%82%E0%A6%B2%E0%A6%BE%E0%A6%A6%E0%A7%87%E0%A6%B6%E0%A6%BF-%E0%A6%B6%E0%A6%BE%E0%A6%B9%E0%A6%BE%E0%A6%A8%E0%A6%BE%E0%A6%B0","source_name":"Prthom Alo","news_language":"Bangla"},{"name":"সাকিবের শীর্ষ স্থানে ভাগ বসালেন নবী","link":"https://www.prothomalo.com/sports/cricket/%E0%A6%B8%E0%A6%BE%E0%A6%95%E0%A6%BF%E0%A6%AC%E0%A7%87%E0%A6%B0-%E0%A6%B6%E0%A7%80%E0%A6%B0%E0%A7%8D%E0%A6%B7-%E0%A6%B8%E0%A7%8D%E0%A6%A5%E0%A6%BE%E0%A6%A8%E0%A7%87-%E0%A6%AD%E0%A6%BE%E0%A6%97-%E0%A6%AC%E0%A6%B8%E0%A6%BE%E0%A6%B2%E0%A7%87%E0%A6%A8-%E0%A6%A8%E0%A6%AC%E0%A7%80","source_name":"Prthom Alo","news_language":"Bangla"},{"name":"দেশে করোনায় ৭ জনের মৃত্যু, শনাক্ত ২৫৬","link":"https://www.prothomalo.com/bangladesh/coronavirus/%E0%A6%A6%E0%A7%87%E0%A6%B6%E0%A7%87-%E0%A6%95%E0%A6%B0%E0%A7%8B%E0%A6%A8%E0%A6%BE%E0%A7%9F-%E0%A7%AD-%E0%A6%9C%E0%A6%A8%E0%A7%87%E0%A6%B0-%E0%A6%AE%E0%A7%83%E0%A6%A4%E0%A7%8D%E0%A6%AF%E0%A7%81-%E0%A6%B6%E0%A6%A8%E0%A6%BE%E0%A6%95%E0%A7%8D%E0%A6%A4-%E0%A7%A8%E0%A7%AB%E0%A7%AC","source_name":"Prthom Alo","news_language":"Bangla"},{"name":"হকিং, আইনস্টাইন ও মেরিলিন মনরো","link":"https://www.prothomalo.com/education/science/%E0%A6%B9%E0%A6%95%E0%A6%BF%E0%A6%82-%E0%A6%86%E0%A6%87%E0%A6%A8%E0%A6%B8%E0%A7%8D%E0%A6%9F%E0%A6%BE%E0%A6%87%E0%A6%A8-%E0%A6%93-%E0%A6%AE%E0%A7%87%E0%A6%B0%E0%A6%BF%E0%A6%B2%E0%A6%BF%E0%A6%A8-%E0%A6%AE%E0%A6%A8%E0%A6%B0%E0%A7%8B","source_name":"Prthom Alo","news_language":"Bangla"},{"name":"বিএনপি সম্পর্কে না বললে আ.লীগ নেতাদের দিন শুরু হয় না","link":"https://www.prothomalo.com/politics/%E0%A6%AC%E0%A6%BF%E0%A6%8F%E0%A6%A8%E0%A6%AA%E0%A6%BF-%E0%A6%B8%E0%A6%AE%E0%A7%8D%E0%A6%AA%E0%A6%B0%E0%A7%8D%E0%A6%95%E0%A7%87-%E0%A6%A8%E0%A6%BE-%E0%A6%AC%E0%A6%B2%E0%A6%B2%E0%A7%87-%E0%A6%86%E0%A6%B2%E0%A7%80%E0%A6%97-%E0%A6%A8%E0%A7%87%E0%A6%A4%E0%A6%BE%E0%A6%A6%E0%A7%87%E0%A6%B0-%E0%A6%A6%E0%A6%BF%E0%A6%A8-%E0%A6%B6%E0%A7%81%E0%A6%B0%E0%A7%81-%E0%A6%B9%E0%A7%9F-%E0%A6%A8%E0%A6%BE","source_name":"Prthom Alo","news_language":"Bangla"},{"name":"আইইউটিতে প্রথম, মেডিকেলে ৫৯তম, ঢাবিতেও প্রথম বগুড়ার মেফতাউল","link":"https://www.prothomalo.com/education/higher-education/%E0%A6%86%E0%A6%87%E0%A6%87%E0%A6%89%E0%A6%9F%E0%A6%BF%E0%A6%A4%E0%A7%87-%E0%A6%AA%E0%A7%8D%E0%A6%B0%E0%A6%A5%E0%A6%AE-%E0%A6%AE%E0%A7%87%E0%A6%A1%E0%A6%BF%E0%A6%95%E0%A7%87%E0%A6%B2%E0%A7%87-%E0%A7%AB%E0%A7%AF%E0%A6%A4%E0%A6%AE-%E0%A6%A2%E0%A6%BE%E0%A6%AC%E0%A6%BF%E0%A6%A4%E0%A7%87%E0%A6%93-%E0%A6%AA%E0%A7%8D%E0%A6%B0%E0%A6%A5%E0%A6%AE-%E0%A6%AC%E0%A6%97%E0%A7%81%E0%A6%A1%E0%A6%BC%E0%A6%BE%E0%A6%B0-%E0%A6%AE%E0%A7%87%E0%A6%AB%E0%A6%A4%E0%A6%BE%E0%A6%89%E0%A6%B2","source_name":"Prthom Alo","news_language":"Bangla"},{"name":"ঐশ্বরিয়া নয়, ‘উমরাওজান’-এর জন্য পছন্দ ছিল অন্য কেউ","link":"https://www.prothomalo.com/entertainment/bollywood/%E0%A6%90%E0%A6%B6%E0%A7%8D%E0%A6%AC%E0%A6%B0%E0%A6%BF%E0%A7%9F%E0%A6%BE-%E0%A6%A8%E0%A7%9F-%E0%A6%89%E0%A6%AE%E0%A6%B0%E0%A6%BE%E0%A6%93%E0%A6%9C%E0%A6%BE%E0%A6%A8-%E0%A6%8F%E0%A6%B0-%E0%A6%9C%E0%A6%A8%E0%A7%8D%E0%A6%AF-%E0%A6%AA%E0%A6%9B%E0%A6%A8%E0%A7%8D%E0%A6%A6-%E0%A6%9B%E0%A6%BF%E0%A6%B2-%E0%A6%85%E0%A6%A8%E0%A7%8D%E0%A6%AF-%E0%A6%95%E0%A7%87%E0%A6%89","source_name":"Prthom Alo","news_language":"Bangla"},{"name":"প্রাতিষ্ঠানিক স্বাভাবিক প্রসব কমেছে ১৬%","link":"https://www.prothomalo.com/bangladesh/%E0%A6%AA%E0%A7%8D%E0%A6%B0%E0%A6%BE%E0%A6%A4%E0%A6%BF%E0%A6%B7%E0%A7%8D%E0%A6%A0%E0%A6%BE%E0%A6%A8%E0%A6%BF%E0%A6%95-%E0%A6%B8%E0%A7%8D%E0%A6%AC%E0%A6%BE%E0%A6%AD%E0%A6%BE%E0%A6%AC%E0%A6%BF%E0%A6%95-%E0%A6%AA%E0%A7%8D%E0%A6%B0%E0%A6%B8%E0%A6%AC-%E0%A6%95%E0%A6%AE%E0%A7%87%E0%A6%9B%E0%A7%87-%E0%A7%A7%E0%A7%AC","source_name":"Prthom Alo","news_language":"Bangla"},{"name":"ভারত দেখাচ্ছে, ইচ্ছা থাকলে ফুটবলে অনেক কিছুই হয়","link":"https://www.prothomalo.com/sports/cricket/%E0%A6%AD%E0%A6%BE%E0%A6%B0%E0%A6%A4-%E0%A6%A6%E0%A7%87%E0%A6%96%E0%A6%BE%E0%A6%9A%E0%A7%8D%E0%A6%9B%E0%A7%87-%E0%A6%87%E0%A6%9A%E0%A7%8D%E0%A6%9B%E0%A6%BE-%E0%A6%A5%E0%A6%BE%E0%A6%95%E0%A6%B2%E0%A7%87-%E0%A6%AB%E0%A7%81%E0%A6%9F%E0%A6%AC%E0%A6%B2%E0%A7%87-%E0%A6%85%E0%A6%A8%E0%A7%87%E0%A6%95-%E0%A6%95%E0%A6%BF%E0%A6%9B%E0%A7%81%E0%A6%87-%E0%A6%B9%E0%A7%9F","source_name":"Prthom Alo","news_language":"Bangla"},{"name":"যে কারণে জলবায়ু সম্মেলন ব্যর্থ হবে","link":"https://www.prothomalo.com/opinion/column/%E0%A6%AF%E0%A7%87-%E0%A6%95%E0%A6%BE%E0%A6%B0%E0%A6%A3%E0%A7%87-%E0%A6%9C%E0%A6%B2%E0%A6%AC%E0%A6%BE%E0%A7%9F%E0%A7%81-%E0%A6%B8%E0%A6%AE%E0%A7%8D%E0%A6%AE%E0%A7%87%E0%A6%B2%E0%A6%A8-%E0%A6%AC%E0%A7%8D%E0%A6%AF%E0%A6%B0%E0%A7%8D%E0%A6%A5-%E0%A6%B9%E0%A6%AC%E0%A7%87","source_name":"Prthom Alo","news_language":"Bangla"},{"name":false,"link":"https://www.prothomalo.com/bangladesh/district/%E0%A6%B8%E0%A7%8B%E0%A6%A8%E0%A6%BE%E0%A6%A4%E0%A6%B2%E0%A6%BE-%E0%A6%AA%E0%A7%8C%E0%A6%B0-%E0%A6%A8%E0%A6%BF%E0%A6%B0%E0%A7%8D%E0%A6%AC%E0%A6%BE%E0%A6%9A%E0%A6%A8%E0%A7%8B%E0%A6%A4%E0%A7%8D%E0%A6%A4%E0%A6%B0-%E0%A6%B8%E0%A6%B9%E0%A6%BF%E0%A6%82%E0%A6%B8%E0%A6%A4%E0%A6%BE%E0%A7%9F-%E0%A6%AC%E0%A6%BF%E0%A6%9C%E0%A7%9F%E0%A7%80-%E0%A6%AE%E0%A7%87%E0%A7%9F%E0%A6%B0-%E0%A6%93-%E0%A6%89%E0%A6%AA%E0%A6%9C%E0%A7%87%E0%A6%B2%E0%A6%BE-%E0%A6%9A%E0%A7%87%E0%A7%9F%E0%A6%BE%E0%A6%B0%E0%A6%AE%E0%A7%8D%E0%A6%AF%E0%A6%BE%E0%A6%A8%E0%A6%B8%E0%A6%B9-%E0%A6%86%E0%A6%B9%E0%A6%A4-%E0%A7%AD","source_name":"Prthom Alo","news_language":"Bangla"},{"name":false,"link":"https://www.prothomalo.com/bangladesh/district/%E0%A6%A8%E0%A6%BE%E0%A6%A8%E0%A7%8D%E0%A6%A6%E0%A6%BE%E0%A6%87%E0%A6%B2%E0%A7%87-%E0%A6%87%E0%A6%9C%E0%A6%BF%E0%A6%AC%E0%A6%BE%E0%A6%87%E0%A6%95%E0%A6%9A%E0%A6%BE%E0%A6%B2%E0%A6%95%E0%A7%87%E0%A6%B0-%E0%A6%B2%E0%A6%BE%E0%A6%B6-%E0%A6%89%E0%A6%A6%E0%A7%8D%E0%A6%A7%E0%A6%BE%E0%A6%B0","source_name":"Prthom Alo","news_language":"Bangla"},{"name":false,"link":"https://www.prothomalo.com/bangladesh/district/%E0%A6%8F%E0%A6%95%E0%A6%87-%E0%A6%AD%E0%A6%AC%E0%A6%A8%E0%A7%87-%E0%A6%97%E0%A7%8D%E0%A6%AF%E0%A6%BE%E0%A6%B8%E0%A7%87%E0%A6%B0-%E0%A6%86%E0%A6%97%E0%A7%81%E0%A6%A8%E0%A7%87-%E0%A6%B9%E0%A6%A4%E0%A6%BE%E0%A6%B9%E0%A6%A4-%E0%A6%AD%E0%A6%AC%E0%A6%A8%E0%A6%AE%E0%A6%BE%E0%A6%B2%E0%A6%BF%E0%A6%95-%E0%A6%B0%E0%A6%BF%E0%A6%AE%E0%A6%BE%E0%A6%A8%E0%A7%8D%E0%A6%A1%E0%A7%87","source_name":"Prthom Alo","news_language":"Bangla"},{"name":"৫০০ উইকেটে ক্লাবে এনামুল জুনিয়র","link":"https://www.prothomalo.com/sports/cricket/%E0%A7%AB%E0%A7%A6%E0%A7%A6-%E0%A6%89%E0%A6%87%E0%A6%95%E0%A7%87%E0%A6%9F%E0%A7%87-%E0%A6%95%E0%A7%8D%E0%A6%B2%E0%A6%BE%E0%A6%AC%E0%A7%87-%E0%A6%8F%E0%A6%A8%E0%A6%BE%E0%A6%AE%E0%A7%81%E0%A6%B2-%E0%A6%9C%E0%A7%81%E0%A6%A8%E0%A6%BF%E0%A7%9F%E0%A6%B0","source_name":"Prthom Alo","news_language":"Bangla"},{"name":"এবার একই দিন সকাল, দুপুর ও বিকেলে ১৯ প্রতিষ্ঠানের চাকরির পরীক্ষা","link":"https://www.prothomalo.com/chakri/employment/%E0%A6%8F%E0%A6%AC%E0%A6%BE%E0%A6%B0-%E0%A6%8F%E0%A6%95%E0%A6%87-%E0%A6%A6%E0%A6%BF%E0%A6%A8-%E0%A6%B8%E0%A6%95%E0%A6%BE%E0%A6%B2-%E0%A6%A6%E0%A7%81%E0%A6%AA%E0%A7%81%E0%A6%B0-%E0%A6%93-%E0%A6%AC%E0%A6%BF%E0%A6%95%E0%A7%87%E0%A6%B2%E0%A7%87-%E0%A7%A7%E0%A7%AF-%E0%A6%AA%E0%A7%8D%E0%A6%B0%E0%A6%A4%E0%A6%BF%E0%A6%B7%E0%A7%8D%E0%A6%A0%E0%A6%BE%E0%A6%A8%E0%A7%87%E0%A6%B0-%E0%A6%9A%E0%A6%BE%E0%A6%95%E0%A6%B0%E0%A6%BF%E0%A6%B0-%E0%A6%AA%E0%A6%B0%E0%A7%80%E0%A6%95%E0%A7%8D%E0%A6%B7%E0%A6%BE","source_name":"Prthom Alo","news_language":"Bangla"},{"name":"ছালেহ আহমেদ তলিয়ে যাওয়ার দায় সিডিএ-চসিকের","link":"https://www.prothomalo.com/bangladesh/district/%E0%A6%9B%E0%A6%BE%E0%A6%B2%E0%A7%87%E0%A6%B9-%E0%A6%86%E0%A6%B9%E0%A6%AE%E0%A7%87%E0%A6%A6-%E0%A6%A4%E0%A6%B2%E0%A6%BF%E0%A7%9F%E0%A7%87-%E0%A6%AF%E0%A6%BE%E0%A6%93%E0%A7%9F%E0%A6%BE%E0%A6%B0-%E0%A6%A6%E0%A6%BE%E0%A7%9F-%E0%A6%B8%E0%A6%BF%E0%A6%A1%E0%A6%BF%E0%A6%8F-%E0%A6%9A%E0%A6%B8%E0%A6%BF%E0%A6%95%E0%A7%87%E0%A6%B0","source_name":"Prthom Alo","news_language":"Bangla"}]