[{"name":"১২৫ রানের লক্ষ্যে ব্যাটিংয়ে পাকিস্তান ","link":"https://www.prothomalo.com/sports/cricket/%E0%A6%9F%E0%A6%B8-%E0%A6%9C%E0%A6%BF%E0%A6%A4%E0%A7%87-%E0%A6%86%E0%A6%9C%E0%A6%93-%E0%A6%AC%E0%A7%8D%E0%A6%AF%E0%A6%BE%E0%A6%9F%E0%A6%BF%E0%A6%82%E0%A7%9F%E0%A7%87-%E0%A6%AC%E0%A6%BE%E0%A6%82%E0%A6%B2%E0%A6%BE%E0%A6%A6%E0%A7%87%E0%A6%B6","source_name":"Prthom Alo","news_language":"Bangla"},{"name":"সময় এখন ব্যাডমিন্টনের","link":"https://www.kishoralo.com/sports/%E0%A6%B8%E0%A6%AE%E0%A7%9F-%E0%A6%8F%E0%A6%96%E0%A6%A8-%E0%A6%AC%E0%A7%8D%E0%A6%AF%E0%A6%BE%E0%A6%A1%E0%A6%AE%E0%A6%BF%E0%A6%A8%E0%A7%8D%E0%A6%9F%E0%A6%A8%E0%A7%87%E0%A6%B0","source_name":"Prthom Alo","news_language":"Bangla"},{"name":"যে আয়ের জন্য কর দিতে হবে না","link":"https://www.prothomalo.com/business/personal-finance/%E0%A6%AF%E0%A7%87-%E0%A6%86%E0%A7%9F%E0%A7%87%E0%A6%B0-%E0%A6%9C%E0%A6%A8%E0%A7%8D%E0%A6%AF-%E0%A6%95%E0%A6%B0-%E0%A6%A6%E0%A6%BF%E0%A6%A4%E0%A7%87-%E0%A6%B9%E0%A6%AC%E0%A7%87-%E0%A6%A8%E0%A6%BE","source_name":"Prthom Alo","news_language":"Bangla"},{"name":"বয়স্ক ভাতার পাশাপাশি শীতবস্ত্রও প্রদান করা হয়","link":"https://trust.prothomalo.com/activities/saadat-smriti-polli/%E0%A6%AC%E0%A7%9F%E0%A6%B8%E0%A7%8D%E0%A6%95-%E0%A6%AD%E0%A6%BE%E0%A6%A4%E0%A6%BE%E0%A6%B0-%E0%A6%AA%E0%A6%BE%E0%A6%B6%E0%A6%BE%E0%A6%AA%E0%A6%BE%E0%A6%B6%E0%A6%BF-%E0%A6%B6%E0%A7%80%E0%A6%A4%E0%A6%AC%E0%A6%B8%E0%A7%8D%E0%A6%A4%E0%A7%8D%E0%A6%B0%E0%A6%93-%E0%A6%AA%E0%A7%8D%E0%A6%B0%E0%A6%A6%E0%A6%BE%E0%A6%A8-%E0%A6%95%E0%A6%B0%E0%A6%BE-%E0%A6%B9%E0%A7%9F","source_name":"Prthom Alo","news_language":"Bangla"},{"name":"কাজ শেষে বাড়ি ফেরা হলো না রনির","link":"https://www.prothomalo.com/bangladesh/district/%E0%A6%95%E0%A6%BE%E0%A6%9C-%E0%A6%B6%E0%A7%87%E0%A6%B7%E0%A7%87-%E0%A6%AC%E0%A6%BE%E0%A7%9C%E0%A6%BF-%E0%A6%AB%E0%A7%87%E0%A6%B0%E0%A6%BE-%E0%A6%B9%E0%A6%B2%E0%A7%8B-%E0%A6%A8%E0%A6%BE-%E0%A6%B0%E0%A6%A8%E0%A6%BF%E0%A6%B0","source_name":"Prthom Alo","news_language":"Bangla"},{"name":false,"link":"https://www.prothomalo.com/bangladesh/district/%E0%A6%B2%E0%A6%95%E0%A7%8D%E0%A6%B7%E0%A7%8D%E0%A6%AE%E0%A7%80%E0%A6%AA%E0%A7%81%E0%A6%B0%E0%A7%87-%E0%A6%95%E0%A6%BF%E0%A6%B6%E0%A7%8B%E0%A6%B0-%E0%A6%9A%E0%A6%BE%E0%A6%B2%E0%A6%95%E0%A6%95%E0%A7%87-%E0%A6%B9%E0%A6%A4%E0%A7%8D%E0%A6%AF%E0%A6%BE-%E0%A6%95%E0%A6%B0%E0%A7%87-%E0%A6%AC%E0%A7%8D%E0%A6%AF%E0%A6%BE%E0%A6%9F%E0%A6%BE%E0%A6%B0%E0%A6%BF%E0%A6%9A%E0%A6%BE%E0%A6%B2%E0%A6%BF%E0%A6%A4-%E0%A6%B0%E0%A6%BF%E0%A6%95%E0%A6%B6%E0%A6%BE-%E0%A6%9B%E0%A6%BF%E0%A6%A8%E0%A6%A4%E0%A6%BE%E0%A6%87","source_name":"Prthom Alo","news_language":"Bangla"},{"name":"সান্ত্বনার খোঁজে নামার আগে চোটে ভুগছে বাংলাদেশ","link":"https://www.prothomalo.com/video/sports/%E0%A6%B8%E0%A6%BE%E0%A6%A8%E0%A7%8D%E0%A6%A4%E0%A7%8D%E0%A6%AC%E0%A6%A8%E0%A6%BE%E0%A6%B0-%E0%A6%96%E0%A7%8B%E0%A6%81%E0%A6%9C%E0%A7%87-%E0%A6%A8%E0%A6%BE%E0%A6%AE%E0%A6%BE%E0%A6%B0-%E0%A6%86%E0%A6%97%E0%A7%87-%E0%A6%9A%E0%A7%8B%E0%A6%9F%E0%A7%87-%E0%A6%AD%E0%A7%81%E0%A6%97%E0%A6%9B%E0%A7%87-%E0%A6%AC%E0%A6%BE%E0%A6%82%E0%A6%B2%E0%A6%BE%E0%A6%A6%E0%A7%87%E0%A6%B6-3","source_name":"Prthom Alo","news_language":"Bangla"},{"name":"জনতা ব্যাংকের দুই পদের এমসিকিউ পরীক্ষার সূচি ও কেন্দ্র প্রকাশ","link":"https://www.prothomalo.com/chakri/employment/%E0%A6%9C%E0%A6%A8%E0%A6%A4%E0%A6%BE-%E0%A6%AC%E0%A7%8D%E0%A6%AF%E0%A6%BE%E0%A6%82%E0%A6%95%E0%A7%87%E0%A6%B0-%E0%A6%A6%E0%A7%81%E0%A6%87-%E0%A6%AA%E0%A6%A6%E0%A7%87%E0%A6%B0-%E0%A6%8F%E0%A6%AE%E0%A6%B8%E0%A6%BF%E0%A6%95%E0%A6%BF%E0%A6%89-%E0%A6%AA%E0%A6%B0%E0%A7%80%E0%A6%95%E0%A7%8D%E0%A6%B7%E0%A6%BE%E0%A6%B0-%E0%A6%B8%E0%A7%82%E0%A6%9A%E0%A6%BF-%E0%A6%93-%E0%A6%95%E0%A7%87%E0%A6%A8%E0%A7%8D%E0%A6%A6%E0%A7%8D%E0%A6%B0-%E0%A6%AA%E0%A7%8D%E0%A6%B0%E0%A6%95%E0%A6%BE%E0%A6%B6","source_name":"Prthom Alo","news_language":"Bangla"},{"name":"পাকিস্তানি জার্সি পরে মাঠে আসার প্রতিবাদ","link":"https://www.prothomalo.com/video/bangladesh/%E0%A6%AA%E0%A6%BE%E0%A6%95%E0%A6%BF%E0%A6%B8%E0%A7%8D%E0%A6%A4%E0%A6%BE%E0%A6%A8%E0%A6%BF-%E0%A6%9C%E0%A6%BE%E0%A6%B0%E0%A7%8D%E0%A6%B8%E0%A6%BF-%E0%A6%AA%E0%A6%B0%E0%A7%87-%E0%A6%AE%E0%A6%BE%E0%A6%A0%E0%A7%87-%E0%A6%86%E0%A6%B8%E0%A6%BE%E0%A6%B0-%E0%A6%AA%E0%A7%8D%E0%A6%B0%E0%A6%A4%E0%A6%BF%E0%A6%AC%E0%A6%BE%E0%A6%A6","source_name":"Prthom Alo","news_language":"Bangla"},{"name":"হাফ পাস শিক্ষার্থীদের অধিকার: যাত্রী কল্যাণ সমিতি","link":"https://www.prothomalo.com/bangladesh/capital/%E0%A6%B9%E0%A6%BE%E0%A6%AB-%E0%A6%AA%E0%A6%BE%E0%A6%B8-%E0%A6%A6%E0%A6%BE%E0%A6%AC%E0%A6%BF-%E0%A6%A8%E0%A7%9F-%E0%A6%B6%E0%A6%BF%E0%A6%95%E0%A7%8D%E0%A6%B7%E0%A6%BE%E0%A6%B0%E0%A7%8D%E0%A6%A5%E0%A7%80%E0%A6%A6%E0%A7%87%E0%A6%B0-%E0%A6%85%E0%A6%A7%E0%A6%BF%E0%A6%95%E0%A6%BE%E0%A6%B0-%E0%A6%AF%E0%A6%BE%E0%A6%A4%E0%A7%8D%E0%A6%B0%E0%A7%80-%E0%A6%95%E0%A6%B2%E0%A7%8D%E0%A6%AF%E0%A6%BE%E0%A6%A3-%E0%A6%B8%E0%A6%AE%E0%A6%BF%E0%A6%A4%E0%A6%BF","source_name":"Prthom Alo","news_language":"Bangla"},{"name":"ইমনের নামে মসলার ব্র্যান্ড","link":"https://www.prothomalo.com/business/%E0%A6%89%E0%A6%A6%E0%A7%8D%E0%A6%AF%E0%A7%8B%E0%A6%95%E0%A7%8D%E0%A6%A4%E0%A6%BE/%E0%A6%87%E0%A6%AE%E0%A6%A8%E0%A7%87%E0%A6%B0-%E0%A6%A8%E0%A6%BE%E0%A6%AE%E0%A7%87-%E0%A6%AE%E0%A6%B8%E0%A6%B2%E0%A6%BE%E0%A6%B0-%E0%A6%AC%E0%A7%8D%E0%A6%B0%E0%A7%8D%E0%A6%AF%E0%A6%BE%E0%A6%A8%E0%A7%8D%E0%A6%A1","source_name":"Prthom Alo","news_language":"Bangla"},{"name":false,"link":"https://www.prothomalo.com/bangladesh/district/%E0%A6%B8%E0%A7%9C%E0%A6%95-%E0%A6%A6%E0%A7%81%E0%A6%B0%E0%A7%8D%E0%A6%98%E0%A6%9F%E0%A6%A8%E0%A6%BE%E0%A7%9F-%E0%A7%A7%E0%A7%AC-%E0%A6%A6%E0%A6%BF%E0%A6%A8-%E0%A6%85%E0%A6%9A%E0%A7%87%E0%A6%A4%E0%A6%A8-%E0%A6%A5%E0%A6%BE%E0%A6%95%E0%A6%BE%E0%A6%B0-%E0%A6%AA%E0%A6%B0-%E0%A6%B8%E0%A7%8C%E0%A6%A6%E0%A6%BF%E0%A6%AA%E0%A7%8D%E0%A6%B0%E0%A6%AC%E0%A6%BE%E0%A6%B8%E0%A7%80-%E0%A6%AF%E0%A7%81%E0%A6%AC%E0%A6%95%E0%A7%87%E0%A6%B0-%E0%A6%AE%E0%A7%83%E0%A6%A4%E0%A7%8D%E0%A6%AF%E0%A7%81","source_name":"Prthom Alo","news_language":"Bangla"},{"name":"‘হাফ পাসের’ দাবিতে অবরোধ আশ্বাসে প্রত্যাহার","link":"https://www.prothomalo.com/bangladesh/capital/%E0%A6%B9%E0%A6%BE%E0%A6%AB-%E0%A6%AA%E0%A6%BE%E0%A6%B8%E0%A7%87%E0%A6%B0-%E0%A6%A6%E0%A6%BE%E0%A6%AC%E0%A6%BF%E0%A6%A4%E0%A7%87-%E0%A6%85%E0%A6%AC%E0%A6%B0%E0%A7%8B%E0%A6%A7-%E0%A6%86%E0%A6%B6%E0%A7%8D%E0%A6%AC%E0%A6%BE%E0%A6%B8%E0%A7%87-%E0%A6%AA%E0%A7%8D%E0%A6%B0%E0%A6%A4%E0%A7%8D%E0%A6%AF%E0%A6%BE%E0%A6%B9%E0%A6%BE%E0%A6%B0","source_name":"Prthom Alo","news_language":"Bangla"},{"name":"শীতের ত্বকে উজ্জ্বলতা...","link":"https://www.prothomalo.com/feature/naksha/%E0%A6%B6%E0%A7%80%E0%A6%A4%E0%A7%87%E0%A6%B0-%E0%A6%A4%E0%A7%8D%E0%A6%AC%E0%A6%95%E0%A7%87-%E0%A6%89%E0%A6%9C%E0%A7%8D%E0%A6%9C%E0%A7%8D%E0%A6%AC%E0%A6%B2%E0%A6%A4%E0%A6%BE","source_name":"Prthom Alo","news_language":"Bangla"},{"name":"অমিত শাহর দপ্তরের সামনে প্রতিবাদী ধরনায় তৃণমূল সাংসদেরা","link":"https://www.prothomalo.com/world/india/%E0%A6%85%E0%A6%AE%E0%A6%BF%E0%A6%A4-%E0%A6%B6%E0%A6%BE%E0%A6%B9%E0%A6%B0-%E0%A6%A6%E0%A6%AA%E0%A7%8D%E0%A6%A4%E0%A6%B0%E0%A7%87%E0%A6%B0-%E0%A6%B8%E0%A6%BE%E0%A6%AE%E0%A6%A8%E0%A7%87-%E0%A6%AA%E0%A7%8D%E0%A6%B0%E0%A6%A4%E0%A6%BF%E0%A6%AC%E0%A6%BE%E0%A6%A6%E0%A7%80-%E0%A6%A7%E0%A6%B0%E0%A6%A8%E0%A6%BE%E0%A7%9F-%E0%A6%A4%E0%A7%83%E0%A6%A3%E0%A6%AE%E0%A7%82%E0%A6%B2-%E0%A6%B8%E0%A6%BE%E0%A6%82%E0%A6%B8%E0%A6%A6%E0%A7%87%E0%A6%B0%E0%A6%BE","source_name":"Prthom Alo","news_language":"Bangla"},{"name":"পেইনের অশ্লীল মেসেজের শিকার নারী দাবি করেছিলেন সাড়ে ৩৪ লাখ টাকা","link":"https://www.prothomalo.com/sports/cricket/%E0%A6%AA%E0%A7%87%E0%A6%87%E0%A6%A8%E0%A7%87%E0%A6%B0-%E0%A6%85%E0%A6%B6%E0%A7%8D%E0%A6%B2%E0%A7%80%E0%A6%B2-%E0%A6%AE%E0%A7%87%E0%A6%B8%E0%A7%87%E0%A6%9C%E0%A7%87%E0%A6%B0-%E0%A6%B6%E0%A6%BF%E0%A6%95%E0%A6%BE%E0%A6%B0-%E0%A6%A8%E0%A6%BE%E0%A6%B0%E0%A7%80-%E0%A6%A6%E0%A6%BE%E0%A6%AC%E0%A6%BF-%E0%A6%95%E0%A6%B0%E0%A7%87%E0%A6%9B%E0%A6%BF%E0%A6%B2%E0%A7%87%E0%A6%A8-%E0%A6%B8%E0%A6%BE%E0%A7%9C%E0%A7%87-%E0%A7%A9%E0%A7%AA-%E0%A6%B2%E0%A6%BE%E0%A6%96-%E0%A6%9F%E0%A6%BE%E0%A6%95%E0%A6%BE","source_name":"Prthom Alo","news_language":"Bangla"}]