[{"name":false,"link":"https://www.prothomalo.com/bangladesh/district/%E0%A6%95%E0%A7%87%E0%A6%B0%E0%A6%BE%E0%A6%A8%E0%A7%80%E0%A6%97%E0%A6%9E%E0%A7%8D%E0%A6%9C%E0%A7%87-%E0%A6%95%E0%A6%BE%E0%A6%B0%E0%A6%BE%E0%A6%97%E0%A6%BE%E0%A6%B0%E0%A7%87-%E0%A6%AC%E0%A6%B8%E0%A7%87-%E0%A6%A2%E0%A6%BE%E0%A6%AC%E0%A6%BF%E0%A6%B0-%E0%A6%AD%E0%A6%B0%E0%A7%8D%E0%A6%A4%E0%A6%BF-%E0%A6%87%E0%A6%9A%E0%A7%8D%E0%A6%9B%E0%A7%81%E0%A6%95-%E0%A6%93-%E0%A6%B8%E0%A7%8D%E0%A6%A8%E0%A6%BE%E0%A6%A4%E0%A6%95%E0%A7%87%E0%A6%B0-%E0%A6%A6%E0%A7%81%E0%A6%87-%E0%A6%B6%E0%A6%BF%E0%A6%95%E0%A7%8D%E0%A6%B7%E0%A6%BE%E0%A6%B0%E0%A7%8D%E0%A6%A5%E0%A7%80%E0%A6%B0-%E0%A6%AA%E0%A6%B0%E0%A7%80%E0%A6%95%E0%A7%8D%E0%A6%B7%E0%A6%BE","source_name":"Prthom Alo","news_language":"Bangla"},{"name":"বিশ্বের জলবায়ু পরিবর্তনের প্রভাব, প্রতিকার","link":"https://www.prothomalo.com/life/durporobash/%E0%A6%AC%E0%A6%BF%E0%A6%B6%E0%A7%8D%E0%A6%AC%E0%A7%87%E0%A6%B0-%E0%A6%9C%E0%A6%B2%E0%A6%AC%E0%A6%BE%E0%A7%9F%E0%A7%81-%E0%A6%AA%E0%A6%B0%E0%A6%BF%E0%A6%AC%E0%A6%B0%E0%A7%8D%E0%A6%A4%E0%A6%A8%E0%A7%87%E0%A6%B0-%E0%A6%AA%E0%A7%8D%E0%A6%B0%E0%A6%AD%E0%A6%BE%E0%A6%AC-%E0%A6%AA%E0%A7%8D%E0%A6%B0%E0%A6%A4%E0%A6%BF%E0%A6%95%E0%A6%BE%E0%A6%B0","source_name":"Prthom Alo","news_language":"Bangla"},{"name":"আলাদাই হয়ে গেলেন সামান্থা ও নাগা","link":"https://www.prothomalo.com/entertainment/bollywood/%E0%A6%86%E0%A6%B2%E0%A6%BE%E0%A6%A6%E0%A6%BE%E0%A6%87-%E0%A6%B9%E0%A7%9F%E0%A7%87-%E0%A6%97%E0%A7%87%E0%A6%B2%E0%A7%87%E0%A6%A8-%E0%A6%B8%E0%A6%BE%E0%A6%AE%E0%A6%BE%E0%A6%A8%E0%A7%8D%E0%A6%A5%E0%A6%BE-%E0%A6%93-%E0%A6%A8%E0%A6%BE%E0%A6%97%E0%A6%BE","source_name":"Prthom Alo","news_language":"Bangla"},{"name":"নন্দলাল","link":"https://www.kishoralo.com/kobita/%E0%A6%A8%E0%A6%A8%E0%A7%8D%E0%A6%A6%E0%A6%B2%E0%A6%BE%E0%A6%B2","source_name":"Prthom Alo","news_language":"Bangla"},{"name":"জলবায়ুবান্ধব নগরের পরিকল্পনা এরিক অ্যাডামসের ","link":"https://northamerica.prothomalo.com/new-york/%E0%A6%9C%E0%A6%B2%E0%A6%AC%E0%A6%BE%E0%A7%9F%E0%A7%81%E0%A6%AC%E0%A6%BE%E0%A6%A8%E0%A7%8D%E0%A6%A7%E0%A6%AC-%E0%A6%A8%E0%A6%97%E0%A6%B0%E0%A7%87%E0%A6%B0-%E0%A6%AA%E0%A6%B0%E0%A6%BF%E0%A6%95%E0%A6%B2%E0%A7%8D%E0%A6%AA%E0%A6%A8%E0%A6%BE-%E0%A6%8F%E0%A6%B0%E0%A6%BF%E0%A6%95-%E0%A6%85%E0%A7%8D%E0%A6%AF%E0%A6%BE%E0%A6%A1%E0%A6%BE%E0%A6%AE%E0%A6%B8%E0%A7%87%E0%A6%B0","source_name":"Prthom Alo","news_language":"Bangla"},{"name":"পদ পেতে চাঁপাইনবাবগঞ্জ স্বেচ্ছাসেবক লীগ নেতাদের ডোপ টেস্ট","link":"https://www.prothomalo.com/bangladesh/district/%E0%A6%AA%E0%A6%A6-%E0%A6%AA%E0%A7%87%E0%A6%A4%E0%A7%87-%E0%A6%9A%E0%A6%BE%E0%A6%81%E0%A6%AA%E0%A6%BE%E0%A6%87%E0%A6%A8%E0%A6%AC%E0%A6%BE%E0%A6%AC%E0%A6%97%E0%A6%9E%E0%A7%8D%E0%A6%9C-%E0%A6%B8%E0%A7%8D%E0%A6%AC%E0%A7%87%E0%A6%9A%E0%A7%8D%E0%A6%9B%E0%A6%BE%E0%A6%B8%E0%A7%87%E0%A6%AC%E0%A6%95-%E0%A6%B2%E0%A7%80%E0%A6%97-%E0%A6%A8%E0%A7%87%E0%A6%A4%E0%A6%BE%E0%A6%A6%E0%A7%87%E0%A6%B0-%E0%A6%A1%E0%A7%8B%E0%A6%AA-%E0%A6%9F%E0%A7%87%E0%A6%B8%E0%A7%8D%E0%A6%9F","source_name":"Prthom Alo","news_language":"Bangla"},{"name":"ইংরেজি | Moxie the rabbit","link":"https://www.prothomalo.com/education/%E0%A6%87%E0%A6%82%E0%A6%B0%E0%A7%87%E0%A6%9C%E0%A6%BF-moxie-the-rabbit","source_name":"Prthom Alo","news_language":"Bangla"},{"name":"মেরিন ফিশারিজ একাডেমিতে চাকরির সুযোগ","link":"https://www.prothomalo.com/chakri/employment/%E0%A6%AE%E0%A7%87%E0%A6%B0%E0%A6%BF%E0%A6%A8-%E0%A6%AB%E0%A6%BF%E0%A6%B6%E0%A6%BE%E0%A6%B0%E0%A6%BF%E0%A6%9C-%E0%A6%8F%E0%A6%95%E0%A6%BE%E0%A6%A1%E0%A7%87%E0%A6%AE%E0%A6%BF%E0%A6%A4%E0%A7%87-%E0%A6%9A%E0%A6%BE%E0%A6%95%E0%A6%B0%E0%A6%BF%E0%A6%B0-%E0%A6%B8%E0%A7%81%E0%A6%AF%E0%A7%8B%E0%A6%97","source_name":"Prthom Alo","news_language":"Bangla"},{"name":"নিজের স্ত্রী ও সোফাকেও ফুটবলার ভাবেন গার্দিওলা!","link":"https://www.prothomalo.com/sports/football/%E0%A6%A8%E0%A6%BF%E0%A6%9C%E0%A7%87%E0%A6%B0-%E0%A6%B8%E0%A7%8D%E0%A6%A4%E0%A7%8D%E0%A6%B0%E0%A7%80-%E0%A6%93-%E0%A6%B8%E0%A7%8B%E0%A6%AB%E0%A6%BE%E0%A6%95%E0%A7%87%E0%A6%93-%E0%A6%AB%E0%A7%81%E0%A6%9F%E0%A6%AC%E0%A6%B2%E0%A6%BE%E0%A6%B0-%E0%A6%AD%E0%A6%BE%E0%A6%AC%E0%A7%87%E0%A6%A8-%E0%A6%97%E0%A6%BE%E0%A6%B0%E0%A7%8D%E0%A6%A6%E0%A6%BF%E0%A6%93%E0%A6%B2%E0%A6%BE","source_name":"Prthom Alo","news_language":"Bangla"},{"name":"বাবার সঙ্গে হারিয়ে গেছে আমার স্বপ্ন","link":"https://www.prothomalo.com/feature/holiday/%E0%A6%AC%E0%A6%BE%E0%A6%AC%E0%A6%BE%E0%A6%B0-%E0%A6%B8%E0%A6%99%E0%A7%8D%E0%A6%97%E0%A7%87-%E0%A6%B9%E0%A6%BE%E0%A6%B0%E0%A6%BF%E0%A7%9F%E0%A7%87-%E0%A6%97%E0%A7%87%E0%A6%9B%E0%A7%87-%E0%A6%86%E0%A6%AE%E0%A6%BE%E0%A6%B0-%E0%A6%B8%E0%A7%8D%E0%A6%AC%E0%A6%AA%E0%A7%8D%E0%A6%A8","source_name":"Prthom Alo","news_language":"Bangla"},{"name":"শেহেরীনের হাসিমুখ ভুলি কী করে","link":"https://www.prothomalo.com/feature/holiday/%E0%A6%B6%E0%A7%87%E0%A6%B9%E0%A7%87%E0%A6%B0%E0%A7%80%E0%A6%A8%E0%A7%87%E0%A6%B0-%E0%A6%B9%E0%A6%BE%E0%A6%B8%E0%A6%BF%E0%A6%AE%E0%A7%81%E0%A6%96-%E0%A6%AD%E0%A7%81%E0%A6%B2%E0%A6%BF-%E0%A6%95%E0%A7%80-%E0%A6%95%E0%A6%B0%E0%A7%87","source_name":"Prthom Alo","news_language":"Bangla"},{"name":"কথার ভেলকি","link":"https://northamerica.prothomalo.com/usa/%E0%A6%95%E0%A6%A5%E0%A6%BE%E0%A6%B0-%E0%A6%AD%E0%A7%87%E0%A6%B2%E0%A6%95%E0%A6%BF","source_name":"Prthom Alo","news_language":"Bangla"},{"name":"‘বিদেশি চ্যানেল ক্লিন ফিড না হওয়ায় বছরে ২০০০ কোটি টাকা বিনিয়োগ হয় না’","link":"https://www.prothomalo.com/politics/%E0%A6%AC%E0%A6%BF%E0%A6%A6%E0%A7%87%E0%A6%B6%E0%A6%BF-%E0%A6%9A%E0%A7%8D%E0%A6%AF%E0%A6%BE%E0%A6%A8%E0%A7%87%E0%A6%B2-%E0%A6%95%E0%A7%8D%E0%A6%B2%E0%A6%BF%E0%A6%A8-%E0%A6%AB%E0%A6%BF%E0%A6%A1-%E0%A6%A8%E0%A6%BE-%E0%A6%B9%E0%A6%93%E0%A7%9F%E0%A6%BE%E0%A7%9F-%E0%A6%AC%E0%A6%9B%E0%A6%B0%E0%A7%87-%E0%A7%A8%E0%A7%A6%E0%A7%A6%E0%A7%A6-%E0%A6%95%E0%A7%8B%E0%A6%9F%E0%A6%BF-%E0%A6%9F%E0%A6%BE%E0%A6%95%E0%A6%BE-%E0%A6%AC%E0%A6%BF%E0%A6%A8%E0%A6%BF%E0%A7%9F%E0%A7%8B%E0%A6%97-%E0%A6%B9%E0%A7%9F-%E0%A6%A8%E0%A6%BE","source_name":"Prthom Alo","news_language":"Bangla"},{"name":"যদি এমন হতো","link":"https://www.kishoralo.com/golpo/%E0%A6%AF%E0%A6%A6%E0%A6%BF-%E0%A6%8F%E0%A6%AE%E0%A6%A8-%E0%A6%B9%E0%A6%A4%E0%A7%8B-2","source_name":"Prthom Alo","news_language":"Bangla"},{"name":"মৃতেরা কথা বলছে","link":"https://northamerica.prothomalo.com/literature/%E0%A6%AE%E0%A7%83%E0%A6%A4%E0%A7%87%E0%A6%B0%E0%A6%BE-%E0%A6%95%E0%A6%A5%E0%A6%BE-%E0%A6%AC%E0%A6%B2%E0%A6%9B%E0%A7%87","source_name":"Prthom Alo","news_language":"Bangla"},{"name":"শিশুকন্যার মৃত্যুর কারণ হিসেবে সাইবার হামলাকে দায়ী করলেন মা","link":"https://www.prothomalo.com/education/science-tech/%E0%A6%B6%E0%A6%BF%E0%A6%B6%E0%A7%81%E0%A6%95%E0%A6%A8%E0%A7%8D%E0%A6%AF%E0%A6%BE%E0%A6%B0-%E0%A6%AE%E0%A7%83%E0%A6%A4%E0%A7%8D%E0%A6%AF%E0%A7%81%E0%A6%B0-%E0%A6%95%E0%A6%BE%E0%A6%B0%E0%A6%A3-%E0%A6%B9%E0%A6%BF%E0%A6%B8%E0%A7%87%E0%A6%AC%E0%A7%87-%E0%A6%B8%E0%A6%BE%E0%A6%87%E0%A6%AC%E0%A6%BE%E0%A6%B0-%E0%A6%B9%E0%A6%BE%E0%A6%AE%E0%A6%B2%E0%A6%BE%E0%A6%95%E0%A7%87-%E0%A6%A6%E0%A6%BE%E0%A7%9F%E0%A7%80-%E0%A6%95%E0%A6%B0%E0%A6%B2%E0%A7%87%E0%A6%A8-%E0%A6%AE%E0%A6%BE","source_name":"Prthom Alo","news_language":"Bangla"}]