[{"name":false,"link":"https://www.prothomalo.com/world/usa/%E0%A6%9F%E0%A7%81%E0%A6%87%E0%A6%9F%E0%A6%BE%E0%A6%B0%E0%A7%87%E0%A6%B0-%E0%A6%AC%E0%A6%BF%E0%A6%B0%E0%A7%81%E0%A6%A6%E0%A7%8D%E0%A6%A7%E0%A7%87-%E0%A6%9F%E0%A7%8D%E0%A6%B0%E0%A6%BE%E0%A6%AE%E0%A7%8D%E0%A6%AA%E0%A7%87%E0%A6%B0-%E0%A6%AE%E0%A6%BE%E0%A6%AE%E0%A6%B2%E0%A6%BE","source_name":"Prthom Alo","news_language":"Bangla"},{"name":"এক ঝলক (২৫ সেপ্টেম্বর, ২০২১)","link":"https://www.prothomalo.com/photo/%E0%A6%8F%E0%A6%95-%E0%A6%9D%E0%A6%B2%E0%A6%95-%E0%A7%A8%E0%A7%AB-%E0%A6%B8%E0%A7%87%E0%A6%AA%E0%A7%8D%E0%A6%9F%E0%A7%87%E0%A6%AE%E0%A7%8D%E0%A6%AC%E0%A6%B0-%E0%A7%A8%E0%A7%A6%E0%A7%A8%E0%A7%A7","source_name":"Prthom Alo","news_language":"Bangla"},{"name":"‘ঘটনাচক্রে শিক্ষক’ কেন হচ্ছে, উত্তরটা কে দেবে","link":"https://www.prothomalo.com/opinion/column/%E0%A6%98%E0%A6%9F%E0%A6%A8%E0%A6%BE%E0%A6%9A%E0%A6%95%E0%A7%8D%E0%A6%B0%E0%A7%87-%E0%A6%B6%E0%A6%BF%E0%A6%95%E0%A7%8D%E0%A6%B7%E0%A6%95-%E0%A6%95%E0%A7%87%E0%A6%A8-%E0%A6%B9%E0%A6%9A%E0%A7%8D%E0%A6%9B%E0%A7%87-%E0%A6%89%E0%A6%A4%E0%A7%8D%E0%A6%A4%E0%A6%B0%E0%A6%9F%E0%A6%BE-%E0%A6%95%E0%A7%87-%E0%A6%A6%E0%A7%87%E0%A6%AC%E0%A7%87","source_name":"Prthom Alo","news_language":"Bangla"},{"name":"ইংল্যান্ডপ্রবাসী ফুটবলারের বাংলাদেশের পাসপোর্ট নেই","link":"https://www.prothomalo.com/sports/football/%E0%A6%87%E0%A6%82%E0%A6%B2%E0%A7%8D%E0%A6%AF%E0%A6%BE%E0%A6%A8%E0%A7%8D%E0%A6%A1%E0%A6%AA%E0%A7%8D%E0%A6%B0%E0%A6%AC%E0%A6%BE%E0%A6%B8%E0%A7%80-%E0%A6%AB%E0%A7%81%E0%A6%9F%E0%A6%AC%E0%A6%B2%E0%A6%BE%E0%A6%B0%E0%A7%87%E0%A6%B0-%E0%A6%AC%E0%A6%BE%E0%A6%82%E0%A6%B2%E0%A6%BE%E0%A6%A6%E0%A7%87%E0%A6%B6%E0%A7%87%E0%A6%B0-%E0%A6%AA%E0%A6%BE%E0%A6%B8%E0%A6%AA%E0%A7%8B%E0%A6%B0%E0%A7%8D%E0%A6%9F-%E0%A6%A8%E0%A7%87%E0%A6%87","source_name":"Prthom Alo","news_language":"Bangla"},{"name":"মুক্ত এশিয়া গড়বে কোয়াড","link":"https://www.prothomalo.com/world/asia/%E0%A6%AE%E0%A7%81%E0%A6%95%E0%A7%8D%E0%A6%A4-%E0%A6%8F%E0%A6%B6%E0%A6%BF%E0%A7%9F%E0%A6%BE-%E0%A6%97%E0%A7%9C%E0%A6%AC%E0%A7%87-%E0%A6%95%E0%A7%8B%E0%A7%9F%E0%A6%BE%E0%A6%A1","source_name":"Prthom Alo","news_language":"Bangla"},{"name":false,"link":"https://www.prothomalo.com/bangladesh/district/%E0%A6%AC%E0%A6%BE%E0%A6%B8%E0%A6%B0%E0%A6%98%E0%A6%B0%E0%A7%87-%E0%A6%98%E0%A7%81%E0%A6%AE%E0%A7%87-%E0%A6%A8%E0%A6%AC%E0%A6%AC%E0%A6%A7%E0%A7%82-%E0%A6%86%E0%A7%9C%E0%A6%BE%E0%A7%9F-%E0%A6%AC%E0%A6%B0%E0%A7%87%E0%A6%B0-%E0%A6%9D%E0%A7%81%E0%A6%B2%E0%A6%A8%E0%A7%8D%E0%A6%A4-%E0%A6%B2%E0%A6%BE%E0%A6%B6","source_name":"Prthom Alo","news_language":"Bangla"},{"name":"‘সম্মিলিত উদ্যোগ কখনো বিফল হয় না, করোনা মোকাবিলায় বরিশাল উদাহরণ’","link":"https://www.prothomalo.com/bangladesh/district/%E0%A6%B8%E0%A6%AE%E0%A7%8D%E0%A6%AE%E0%A6%BF%E0%A6%B2%E0%A6%BF%E0%A6%A4-%E0%A6%89%E0%A6%A6%E0%A7%8D%E0%A6%AF%E0%A7%87%E0%A6%BE%E0%A6%97-%E0%A6%95%E0%A6%96%E0%A6%A8%E0%A7%87%E0%A6%BE-%E0%A6%AC%E0%A6%BF%E0%A6%AB%E0%A6%B2-%E0%A6%B9%E0%A7%9F-%E0%A6%A8%E0%A6%BE-%E0%A6%95%E0%A6%B0%E0%A7%87%E0%A6%BE%E0%A6%A8%E0%A6%BE-%E0%A6%AE%E0%A7%87%E0%A6%BE%E0%A6%95%E0%A6%BE%E0%A6%AC%E0%A6%BF%E0%A6%B2%E0%A6%BE%E0%A7%9F-%E0%A6%AC%E0%A6%B0%E0%A6%BF%E0%A6%B6%E0%A6%BE%E0%A6%B2-%E0%A6%89%E0%A6%A6%E0%A6%BE%E0%A6%B9%E0%A6%B0%E0%A6%A3","source_name":"Prthom Alo","news_language":"Bangla"},{"name":"পৃথিবীর কক্ষপথে কতগুলো স্যাটেলাইট ঘুরছে","link":"https://www.prothomalo.com/education/science-tech/%E0%A6%AA%E0%A7%83%E0%A6%A5%E0%A6%BF%E0%A6%AC%E0%A7%80%E0%A6%B0-%E0%A6%95%E0%A6%95%E0%A7%8D%E0%A6%B7%E0%A6%AA%E0%A6%A5%E0%A7%87-%E0%A6%95%E0%A6%A4%E0%A6%97%E0%A7%81%E0%A6%B2%E0%A7%8B-%E0%A6%B8%E0%A7%8D%E0%A6%AF%E0%A6%BE%E0%A6%9F%E0%A7%87%E0%A6%B2%E0%A6%BE%E0%A6%87%E0%A6%9F-%E0%A6%98%E0%A7%81%E0%A6%B0%E0%A6%9B%E0%A7%87","source_name":"Prthom Alo","news_language":"Bangla"},{"name":"বিয়ে না করে সুখে আছি: সালমান","link":"https://www.prothomalo.com/entertainment/bollywood/%E0%A6%AC%E0%A6%BF%E0%A7%9F%E0%A7%87-%E0%A6%A8%E0%A6%BE-%E0%A6%95%E0%A6%B0%E0%A7%87-%E0%A6%B8%E0%A7%81%E0%A6%96%E0%A7%87-%E0%A6%86%E0%A6%9B%E0%A6%BF-%E0%A6%B8%E0%A6%BE%E0%A6%B2%E0%A6%AE%E0%A6%BE%E0%A6%A8","source_name":"Prthom Alo","news_language":"Bangla"},{"name":"বিএনপি সব সময়ই চোরাগলিপথে ক্ষমতায় এসেছে: কৃষিমন্ত্রী","link":"https://www.prothomalo.com/bangladesh/district/%E0%A6%AC%E0%A6%BF%E0%A6%8F%E0%A6%A8%E0%A6%AA%E0%A6%BF-%E0%A6%B8%E0%A6%AC-%E0%A6%B8%E0%A6%AE%E0%A7%9F%E0%A6%87-%E0%A6%9A%E0%A7%8B%E0%A6%B0%E0%A6%BE%E0%A6%97%E0%A6%B2%E0%A6%BF%E0%A6%AA%E0%A6%A5%E0%A7%87-%E0%A6%95%E0%A7%8D%E0%A6%B7%E0%A6%AE%E0%A6%A4%E0%A6%BE%E0%A7%9F-%E0%A6%8F%E0%A6%B8%E0%A7%87%E0%A6%9B%E0%A7%87-%E0%A6%95%E0%A7%83%E0%A6%B7%E0%A6%BF%E0%A6%AE%E0%A6%A8%E0%A7%8D%E0%A6%A4%E0%A7%8D%E0%A6%B0%E0%A7%80","source_name":"Prthom Alo","news_language":"Bangla"},{"name":"ট্যাপ কীভাবে কাজ করে","link":"https://www.kishoralo.com/feature/%E0%A6%9F%E0%A7%8D%E0%A6%AF%E0%A6%BE%E0%A6%AA-%E0%A6%95%E0%A7%80%E0%A6%AD%E0%A6%BE%E0%A6%AC%E0%A7%87-%E0%A6%95%E0%A6%BE%E0%A6%9C-%E0%A6%95%E0%A6%B0%E0%A7%87","source_name":"Prthom Alo","news_language":"Bangla"},{"name":"রিয়ালের কাজটা সহজ করে দিল আতলেতিকো","link":"https://www.prothomalo.com/sports/football/%E0%A6%B0%E0%A6%BF%E0%A7%9F%E0%A6%BE%E0%A6%B2%E0%A7%87%E0%A6%B0-%E0%A6%95%E0%A6%BE%E0%A6%9C%E0%A6%9F%E0%A6%BE-%E0%A6%B8%E0%A6%B9%E0%A6%9C-%E0%A6%95%E0%A6%B0%E0%A7%87-%E0%A6%A6%E0%A6%BF%E0%A6%B2-%E0%A6%86%E0%A6%A4%E0%A6%B2%E0%A7%87%E0%A6%A4%E0%A6%BF%E0%A6%95%E0%A7%8B","source_name":"Prthom Alo","news_language":"Bangla"},{"name":false,"link":"https://www.prothomalo.com/world/asia/%E0%A7%AA-%E0%A6%85%E0%A6%AA%E0%A6%B9%E0%A6%B0%E0%A6%A3%E0%A6%95%E0%A6%BE%E0%A6%B0%E0%A7%80%E0%A6%B0-%E0%A6%B2%E0%A6%BE%E0%A6%B6-%E0%A6%95%E0%A7%8D%E0%A6%B0%E0%A7%87%E0%A6%A8%E0%A7%87-%E0%A6%9D%E0%A7%81%E0%A6%B2%E0%A6%BF%E0%A7%9F%E0%A7%87-%E0%A6%A4%E0%A6%BE%E0%A6%B2%E0%A7%87%E0%A6%AC%E0%A6%BE%E0%A6%A8%E0%A7%87%E0%A6%B0-%E0%A6%B6%E0%A6%BF%E0%A6%95%E0%A7%8D%E0%A6%B7%E0%A6%BE","source_name":"Prthom Alo","news_language":"Bangla"},{"name":"‘লক্ষ্মীপুরে জামায়াত-বিএনপিকে ওরাই আর্থিকভাবে প্রতিষ্ঠিত করেছে’","link":"https://www.prothomalo.com/bangladesh/district/%E0%A6%B2%E0%A6%95%E0%A7%8D%E0%A6%B7%E0%A7%8D%E0%A6%AE%E0%A7%80%E0%A6%AA%E0%A7%81%E0%A6%B0%E0%A7%87-%E0%A6%9C%E0%A6%BE%E0%A6%AE%E0%A6%BE%E0%A7%9F%E0%A6%BE%E0%A6%A4-%E0%A6%AC%E0%A6%BF%E0%A6%8F%E0%A6%A8%E0%A6%AA%E0%A6%BF%E0%A6%95%E0%A7%87-%E0%A6%93%E0%A6%B0%E0%A6%BE%E0%A6%87-%E0%A6%86%E0%A6%B0%E0%A7%8D%E0%A6%A5%E0%A6%BF%E0%A6%95%E0%A6%AD%E0%A6%BE%E0%A6%AC%E0%A7%87-%E0%A6%AA%E0%A7%8D%E0%A6%B0%E0%A6%A4%E0%A6%BF%E0%A6%B7%E0%A7%8D%E0%A6%A0%E0%A6%BF%E0%A6%A4-%E0%A6%95%E0%A6%B0%E0%A7%87%E0%A6%9B%E0%A7%87","source_name":"Prthom Alo","news_language":"Bangla"},{"name":"ব্যবসায় উদ্যোগ | বহুনির্বাচনি প্রশ্ন","link":"https://www.prothomalo.com/education/%E0%A6%AC%E0%A7%8D%E0%A6%AF%E0%A6%AC%E0%A6%B8%E0%A6%BE%E0%A7%9F-%E0%A6%89%E0%A6%A6%E0%A7%8D%E0%A6%AF%E0%A7%8B%E0%A6%97-%E0%A6%AC%E0%A6%B9%E0%A7%81%E0%A6%A8%E0%A6%BF%E0%A6%B0%E0%A7%8D%E0%A6%AC%E0%A6%BE%E0%A6%9A%E0%A6%A8%E0%A6%BF-%E0%A6%AA%E0%A7%8D%E0%A6%B0%E0%A6%B6%E0%A7%8D%E0%A6%A8-48","source_name":"Prthom Alo","news_language":"Bangla"},{"name":"আইভী আমৃত্যু আ.লীগ করবেন, কাজ করবেন দলমতের ঊর্ধ্বে থেকে","link":"https://www.prothomalo.com/bangladesh/district/%E0%A6%86%E0%A6%87%E0%A6%AD%E0%A7%80-%E0%A6%86%E0%A6%AE%E0%A7%83%E0%A6%A4%E0%A7%8D%E0%A6%AF%E0%A7%81-%E0%A6%86%E0%A6%B2%E0%A7%80%E0%A6%97-%E0%A6%95%E0%A6%B0%E0%A6%AC%E0%A7%87%E0%A6%A8-%E0%A6%95%E0%A6%BE%E0%A6%9C-%E0%A6%95%E0%A6%B0%E0%A6%AC%E0%A7%87%E0%A6%A8-%E0%A6%A6%E0%A6%B2%E0%A6%AE%E0%A6%A4%E0%A7%87%E0%A6%B0-%E0%A6%8A%E0%A6%B0%E0%A7%8D%E0%A6%A7%E0%A7%8D%E0%A6%AC%E0%A7%87-%E0%A6%A5%E0%A7%87%E0%A6%95%E0%A7%87","source_name":"Prthom Alo","news_language":"Bangla"}]