[{"name":"পারফরম্যান্সই বলে দিচ্ছে, এটা ‘ফ্লুক’ নয়","link":"https://www.prothomalo.com/sports/cricket/%E0%A6%AA%E0%A6%BE%E0%A6%B0%E0%A6%AB%E0%A6%B0%E0%A6%AE%E0%A7%8D%E0%A6%AF%E0%A6%BE%E0%A6%A8%E0%A7%8D%E0%A6%B8%E0%A6%87-%E0%A6%AC%E0%A6%B2%E0%A7%87-%E0%A6%A6%E0%A6%BF%E0%A6%9A%E0%A7%8D%E0%A6%9B%E0%A7%87-%E0%A6%8F%E0%A6%9F%E0%A6%BE-%E0%A6%AB%E0%A7%8D%E0%A6%B2%E0%A7%81%E0%A6%95-%E0%A6%A8%E0%A7%9F","source_name":"Prthom Alo","news_language":"Bangla"},{"name":"বঙ্গবন্ধু: বাংলার জোছনা ও রোদ্দুর–২৮","link":"http://nagorik.prothomalo.com/%E0%A6%AC%E0%A6%99%E0%A7%8D%E0%A6%97%E0%A6%AC%E0%A6%A8%E0%A7%8D%E0%A6%A7%E0%A7%81-%E0%A6%AC%E0%A6%BE%E0%A6%82%E0%A6%B2%E0%A6%BE%E0%A6%B0-%E0%A6%9C%E0%A7%8B%E0%A6%9B%E0%A6%A8%E0%A6%BE-%E0%A6%93-%E0%A6%B0%E0%A7%8B%E0%A6%A6%E0%A7%8D%E0%A6%A6%E0%A7%81%E0%A6%B0%E0%A7%A8%E0%A7%AE","source_name":"Prthom Alo","news_language":"Bangla"},{"name":"কানাডার ৬ নাগরিকের পরিবারকে ৮ কোটি ডলার ক্ষতিপূরণের ঘোষণা","link":"https://northamerica.prothomalo.com/%E0%A6%95%E0%A6%BE%E0%A6%A8%E0%A6%BE%E0%A6%A1%E0%A6%BE%E0%A6%B0-%E0%A7%AC-%E0%A6%A8%E0%A6%BE%E0%A6%97%E0%A6%B0%E0%A6%BF%E0%A6%95%E0%A7%87%E0%A6%B0-%E0%A6%AA%E0%A6%B0%E0%A6%BF%E0%A6%AC%E0%A6%BE%E0%A6%B0%E0%A6%95%E0%A7%87-%E0%A7%AE-%E0%A6%95%E0%A7%8B%E0%A6%9F%E0%A6%BF-%E0%A6%A1%E0%A6%B2%E0%A6%BE%E0%A6%B0-%E0%A6%95%E0%A7%8D%E0%A6%B7%E0%A6%A4%E0%A6%BF%E0%A6%AA%E0%A7%82%E0%A6%B0%E0%A6%A3%E0%A7%87%E0%A6%B0-%E0%A6%98%E0%A7%8B%E0%A6%B7%E0%A6%A3%E0%A6%BE","source_name":"Prthom Alo","news_language":"Bangla"},{"name":"ভারতে নেতা-নেত্রীদের সম্পত্তি বাড়ছে সাংঘাতিকভাবে","link":"https://www.prothomalo.com/world/india/%E0%A6%AD%E0%A6%BE%E0%A6%B0%E0%A6%A4%E0%A7%87-%E0%A6%A8%E0%A7%87%E0%A6%A4%E0%A6%BE-%E0%A6%A8%E0%A7%87%E0%A6%A4%E0%A7%8D%E0%A6%B0%E0%A7%80%E0%A6%A6%E0%A7%87%E0%A6%B0-%E0%A6%B8%E0%A6%AE%E0%A7%8D%E0%A6%AA%E0%A6%A4%E0%A7%8D%E0%A6%A4%E0%A6%BF-%E0%A6%AC%E0%A6%BE%E0%A6%A1%E0%A6%BC%E0%A6%9B%E0%A7%87-%E0%A6%B8%E0%A6%BE%E0%A6%82%E0%A6%98%E0%A6%BE%E0%A6%A4%E0%A6%BF%E0%A6%95%E0%A6%AD%E0%A6%BE%E0%A6%AC%E0%A7%87","source_name":"Prthom Alo","news_language":"Bangla"},{"name":"নিরাপদে বিদেশ যাওয়া নিয়ে পট লোকগান","link":"https://www.prothomalo.com/video/bangladesh/%E0%A6%A8%E0%A6%BF%E0%A6%B0%E0%A6%BE%E0%A6%AA%E0%A6%A6%E0%A7%87-%E0%A6%AC%E0%A6%BF%E0%A6%A6%E0%A7%87%E0%A6%B6-%E0%A6%AF%E0%A6%BE%E0%A6%93%E0%A6%AF%E0%A6%BC%E0%A6%BE-%E0%A6%A8%E0%A6%BF%E0%A6%AF%E0%A6%BC%E0%A7%87-%E0%A6%AA%E0%A6%9F-%E0%A6%B2%E0%A7%8B%E0%A6%95%E0%A6%97%E0%A6%BE%E0%A6%A8","source_name":"Prthom Alo","news_language":"Bangla"},{"name":"ছয় জেলায় মৃদু শৈত্যপ্রবাহ, রাজধানীসহ সারা দেশে শীত বাড়বে","link":"https://www.prothomalo.com/bangladesh/%E0%A6%9B%E0%A7%9F-%E0%A6%9C%E0%A7%87%E0%A6%B2%E0%A6%BE%E0%A7%9F-%E0%A6%AE%E0%A7%83%E0%A6%A6%E0%A7%81-%E0%A6%B6%E0%A7%88%E0%A6%A4%E0%A7%8D%E0%A6%AF%E0%A6%AA%E0%A7%8D%E0%A6%B0%E0%A6%AC%E0%A6%BE%E0%A6%B9-%E0%A6%B0%E0%A6%BE%E0%A6%9C%E0%A6%A7%E0%A6%BE%E0%A6%A8%E0%A7%80%E0%A6%B8%E0%A6%B9-%E0%A6%B8%E0%A6%BE%E0%A6%B0%E0%A6%BE-%E0%A6%A6%E0%A7%87%E0%A6%B6%E0%A7%87-%E0%A6%B6%E0%A7%80%E0%A6%A4-%E0%A6%AC%E0%A6%BE%E0%A7%9C%E0%A6%AC%E0%A7%87","source_name":"Prthom Alo","news_language":"Bangla"},{"name":"সেদিন মনে হয়েছিল, আমি আর বাঁচব না","link":"https://www.prothomalo.com/entertainment/entertainment-interview/%E0%A6%B8%E0%A7%87%E0%A6%A6%E0%A6%BF%E0%A6%A8-%E0%A6%AE%E0%A6%A8%E0%A7%87-%E0%A6%B9%E0%A7%9F%E0%A7%87%E0%A6%9B%E0%A6%BF%E0%A6%B2-%E0%A6%86%E0%A6%AE%E0%A6%BF-%E0%A6%86%E0%A6%B0-%E0%A6%AC%E0%A6%BE%E0%A6%81%E0%A6%9A%E0%A6%AC-%E0%A6%A8%E0%A6%BE","source_name":"Prthom Alo","news_language":"Bangla"},{"name":"অ্যাম্বুলেন্সে রোগী নয়, বহন করা হচ্ছিল ফেনসিডিল","link":"https://www.prothomalo.com/bangladesh/district/%E0%A6%85%E0%A7%8D%E0%A6%AF%E0%A6%BE%E0%A6%AE%E0%A7%8D%E0%A6%AC%E0%A7%81%E0%A6%B2%E0%A7%87%E0%A6%A8%E0%A7%8D%E0%A6%B8%E0%A7%87-%E0%A6%B0%E0%A7%8B%E0%A6%97%E0%A7%80-%E0%A6%A8%E0%A7%9F-%E0%A6%AC%E0%A6%B9%E0%A6%A8-%E0%A6%95%E0%A6%B0%E0%A6%BE-%E0%A6%B9%E0%A6%9A%E0%A7%8D%E0%A6%9B%E0%A6%BF%E0%A6%B2-%E0%A6%AB%E0%A7%87%E0%A6%A8%E0%A6%B8%E0%A6%BF%E0%A6%A1%E0%A6%BF%E0%A6%B2","source_name":"Prthom Alo","news_language":"Bangla"},{"name":"মধ্যপ্রাচ্যগামীদের জন্য বিমানের ভাড়া কমল","link":"https://www.prothomalo.com/bangladesh/%E0%A6%AE%E0%A6%A7%E0%A7%8D%E0%A6%AF%E0%A6%AA%E0%A7%8D%E0%A6%B0%E0%A6%BE%E0%A6%9A%E0%A7%8D%E0%A6%AF%E0%A6%97%E0%A6%BE%E0%A6%AE%E0%A7%80%E0%A6%A6%E0%A7%87%E0%A6%B0-%E0%A6%9C%E0%A6%A8%E0%A7%8D%E0%A6%AF-%E0%A6%AC%E0%A6%BF%E0%A6%AE%E0%A6%BE%E0%A6%A8%E0%A7%87%E0%A6%B0-%E0%A6%AD%E0%A6%BE%E0%A7%9C%E0%A6%BE-%E0%A6%95%E0%A6%AE%E0%A6%B2","source_name":"Prthom Alo","news_language":"Bangla"},{"name":"বাফুফে একাডেমির বাছাই পরীক্ষায় নরওয়েপ্রবাসী ফুটবলার","link":"https://www.prothomalo.com/sports/football/%E0%A6%AC%E0%A6%BE%E0%A6%AB%E0%A7%81%E0%A6%AB%E0%A7%87-%E0%A6%8F%E0%A6%95%E0%A6%BE%E0%A6%A1%E0%A7%87%E0%A6%AE%E0%A6%BF%E0%A6%B0-%E0%A6%AC%E0%A6%BE%E0%A6%9B%E0%A6%BE%E0%A6%87-%E0%A6%AA%E0%A6%B0%E0%A7%80%E0%A6%95%E0%A7%8D%E0%A6%B7%E0%A6%BE%E0%A7%9F-%E0%A6%A8%E0%A6%B0%E0%A6%93%E0%A7%9F%E0%A7%87%E0%A6%AA%E0%A7%8D%E0%A6%B0%E0%A6%AC%E0%A6%BE%E0%A6%B8%E0%A7%80-%E0%A6%AB%E0%A7%81%E0%A6%9F%E0%A6%AC%E0%A6%B2%E0%A6%BE%E0%A6%B0","source_name":"Prthom Alo","news_language":"Bangla"},{"name":"ছিনতাইমুক্ত নিরাপদ ক্যাম্পাসের দাবি রাবি শিক্ষার্থীদের","link":"https://www.prothomalo.com/bangladesh/district/%E0%A6%9B%E0%A6%BF%E0%A6%A8%E0%A6%A4%E0%A6%BE%E0%A6%87%E0%A6%AE%E0%A7%81%E0%A6%95%E0%A7%8D%E0%A6%A4-%E0%A6%A8%E0%A6%BF%E0%A6%B0%E0%A6%BE%E0%A6%AA%E0%A6%A6-%E0%A6%95%E0%A7%8D%E0%A6%AF%E0%A6%BE%E0%A6%AE%E0%A7%8D%E0%A6%AA%E0%A6%BE%E0%A6%B8%E0%A7%87%E0%A6%B0-%E0%A6%A6%E0%A6%BE%E0%A6%AC%E0%A6%BF-%E0%A6%B0%E0%A6%BE%E0%A6%AC%E0%A6%BF-%E0%A6%B6%E0%A6%BF%E0%A6%95%E0%A7%8D%E0%A6%B7%E0%A6%BE%E0%A6%B0%E0%A7%8D%E0%A6%A5%E0%A7%80%E0%A6%A6%E0%A7%87%E0%A6%B0","source_name":"Prthom Alo","news_language":"Bangla"},{"name":"গাজীপুরে বাসে অগ্নিকাণ্ড, অল্পের জন্য রক্ষা পেলেন চালক ও সহকারী","link":"https://www.prothomalo.com/bangladesh/district/%E0%A6%97%E0%A6%BE%E0%A6%9C%E0%A7%80%E0%A6%AA%E0%A7%81%E0%A6%B0%E0%A7%87-%E0%A6%AC%E0%A6%BE%E0%A6%B8%E0%A7%87-%E0%A6%85%E0%A6%97%E0%A7%8D%E0%A6%A8%E0%A6%BF%E0%A6%95%E0%A6%BE%E0%A6%A3%E0%A7%8D%E0%A6%A1-%E0%A6%85%E0%A6%B2%E0%A7%8D%E0%A6%AA%E0%A7%87%E0%A6%B0-%E0%A6%9C%E0%A6%A8%E0%A7%8D%E0%A6%AF-%E0%A6%B0%E0%A6%95%E0%A7%8D%E0%A6%B7%E0%A6%BE-%E0%A6%AA%E0%A7%87%E0%A6%B2%E0%A7%87%E0%A6%A8-%E0%A6%9A%E0%A6%BE%E0%A6%B2%E0%A6%95-%E0%A6%93-%E0%A6%B8%E0%A6%B9%E0%A6%95%E0%A6%BE%E0%A6%B0%E0%A7%80","source_name":"Prthom Alo","news_language":"Bangla"},{"name":false,"link":"https://www.prothomalo.com/bangladesh/district/%E0%A6%A1%E0%A6%BF%E0%A6%9C%E0%A6%BF%E0%A6%8F%E0%A6%AB%E0%A6%86%E0%A6%87%E0%A7%9F%E0%A7%87%E0%A6%B0-%E0%A6%A8%E0%A6%BE%E0%A6%AE%E0%A7%87-%E0%A6%A4%E0%A7%88%E0%A6%AE%E0%A7%81%E0%A6%B0%E0%A7%87%E0%A6%B0-%E0%A6%95%E0%A6%BE%E0%A6%9B%E0%A7%87-%E0%A6%9A%E0%A6%BE%E0%A6%81%E0%A6%A6%E0%A6%BE-%E0%A6%A6%E0%A6%BE%E0%A6%AC%E0%A6%BF-%E0%A6%95%E0%A6%B0%E0%A6%BE-%E0%A6%AA%E0%A7%8D%E0%A6%B0%E0%A6%A4%E0%A6%BE%E0%A6%B0%E0%A6%95-%E0%A6%97%E0%A7%8D%E0%A6%B0%E0%A7%87%E0%A6%AA%E0%A7%8D%E0%A6%A4%E0%A6%BE%E0%A6%B0","source_name":"Prthom Alo","news_language":"Bangla"},{"name":"ভারত সরকারকে তার চাষিদের বাঁচাতেই হবে","link":"https://www.prothomalo.com/opinion/column/%E0%A6%AD%E0%A6%BE%E0%A6%B0%E0%A6%A4-%E0%A6%B8%E0%A6%B0%E0%A6%95%E0%A6%BE%E0%A6%B0%E0%A6%95%E0%A7%87-%E0%A6%A4%E0%A6%BE%E0%A6%B0-%E0%A6%9A%E0%A6%BE%E0%A6%B7%E0%A6%BF%E0%A6%A6%E0%A7%87%E0%A6%B0-%E0%A6%AC%E0%A6%BE%E0%A6%81%E0%A6%9A%E0%A6%BE%E0%A6%A4%E0%A7%87%E0%A6%87-%E0%A6%B9%E0%A6%AC%E0%A7%87","source_name":"Prthom Alo","news_language":"Bangla"},{"name":"পানির বোতল, কাচের গ্লাস, চামচে সুর তুলতেন তিনি","link":"https://www.prothomalo.com/entertainment/bollywood/%E0%A6%AA%E0%A6%BE%E0%A6%A8%E0%A6%BF%E0%A6%B0-%E0%A6%AC%E0%A7%8B%E0%A6%A4%E0%A6%B2-%E0%A6%95%E0%A6%BE%E0%A6%9A%E0%A7%87%E0%A6%B0-%E0%A6%97%E0%A7%8D%E0%A6%B2%E0%A6%BE%E0%A6%B8-%E0%A6%9A%E0%A6%BE%E0%A6%AE%E0%A6%9A%E0%A7%87-%E0%A6%B8%E0%A7%81%E0%A6%B0-%E0%A6%A4%E0%A7%81%E0%A6%B2%E0%A6%A4%E0%A7%87%E0%A6%A8-%E0%A6%A4%E0%A6%BF%E0%A6%A8%E0%A6%BF","source_name":"Prthom Alo","news_language":"Bangla"},{"name":"কয়েক শ মানুষ দেখেই খেই হারিয়ে ফেলেছেন বিএনপি নেতারা: তথ্যমন্ত্রী","link":"https://www.prothomalo.com/politics/%E0%A6%95%E0%A7%9F%E0%A7%87%E0%A6%95-%E0%A6%B6-%E0%A6%AE%E0%A6%BE%E0%A6%A8%E0%A7%81%E0%A6%B7-%E0%A6%A6%E0%A7%87%E0%A6%96%E0%A7%87%E0%A6%87-%E0%A6%96%E0%A7%87%E0%A6%87-%E0%A6%B9%E0%A6%BE%E0%A6%B0%E0%A6%BF%E0%A7%9F%E0%A7%87-%E0%A6%AB%E0%A7%87%E0%A6%B2%E0%A7%87%E0%A6%9B%E0%A7%87%E0%A6%A8-%E0%A6%AC%E0%A6%BF%E0%A6%8F%E0%A6%A8%E0%A6%AA%E0%A6%BF-%E0%A6%A8%E0%A7%87%E0%A6%A4%E0%A6%BE%E0%A6%B0%E0%A6%BE-%E0%A6%A4%E0%A6%A5%E0%A7%8D%E0%A6%AF%E0%A6%AE%E0%A6%A8%E0%A7%8D%E0%A6%A4%E0%A7%8D%E0%A6%B0%E0%A7%80","source_name":"Prthom Alo","news_language":"Bangla"}]