[{"name":"যে লজ্জার কথায় লাল হয়ে যায় পাকিস্তান","link":"https://www.prothomalo.com/sports/cricket/%E0%A6%AF%E0%A7%87-%E0%A6%B2%E0%A6%9C%E0%A7%8D%E0%A6%9C%E0%A6%BE%E0%A6%B0-%E0%A6%95%E0%A6%A5%E0%A6%BE%E0%A7%9F-%E0%A6%B2%E0%A6%BE%E0%A6%B2-%E0%A6%B9%E0%A7%9F%E0%A7%87-%E0%A6%AF%E0%A6%BE%E0%A7%9F-%E0%A6%AA%E0%A6%BE%E0%A6%95%E0%A6%BF%E0%A6%B8%E0%A7%8D%E0%A6%A4%E0%A6%BE%E0%A6%A8","source_name":"Prthom Alo","news_language":"Bangla"},{"name":"ছাদের মাঝে একটা বাগান","link":"https://www.kishoralo.com/feature/%E0%A6%9B%E0%A6%BE%E0%A6%A6%E0%A7%87%E0%A6%B0-%E0%A6%AE%E0%A6%BE%E0%A6%9D%E0%A7%87-%E0%A6%8F%E0%A6%95%E0%A6%9F%E0%A6%BE-%E0%A6%AC%E0%A6%BE%E0%A6%97%E0%A6%BE%E0%A6%A8","source_name":"Prthom Alo","news_language":"Bangla"},{"name":"বাবুডাইং আলোর পাঠশালায় তৃতীয় পর্যায়ে স্টেম শিক্ষাবিষয়ক কর্মশালা অনুষ্ঠিত","link":"https://trust.prothomalo.com/activities/alor-school/%E0%A6%AC%E0%A6%BE%E0%A6%AC%E0%A7%81%E0%A6%A1%E0%A6%BE%E0%A6%87%E0%A6%82-%E0%A6%86%E0%A6%B2%E0%A7%8B%E0%A6%B0-%E0%A6%AA%E0%A6%BE%E0%A6%A0%E0%A6%B6%E0%A6%BE%E0%A6%B2%E0%A6%BE%E0%A7%9F-%E0%A6%A4%E0%A7%83%E0%A6%A4%E0%A7%80%E0%A7%9F-%E0%A6%AA%E0%A6%B0%E0%A7%8D%E0%A6%AF%E0%A6%BE%E0%A7%9F%E0%A7%87-%E0%A6%B8%E0%A7%8D%E0%A6%9F%E0%A7%87%E0%A6%AE-%E0%A6%B6%E0%A6%BF%E0%A6%95%E0%A7%8D%E0%A6%B7%E0%A6%BE%E0%A6%AC%E0%A6%BF%E0%A6%B7%E0%A7%9F%E0%A6%95-%E0%A6%95%E0%A6%B0%E0%A7%8D%E0%A6%AE%E0%A6%B6%E0%A6%BE%E0%A6%B2%E0%A6%BE-%E0%A6%85%E0%A6%A8%E0%A7%81%E0%A6%B7%E0%A7%8D%E0%A6%A0%E0%A6%BF%E0%A6%A4","source_name":"Prthom Alo","news_language":"Bangla"},{"name":"রকমারি-বিজ্ঞানচিন্তা কুইজ আসছে বিজ্ঞানচিন্তার অক্টোবর সংখ্যায়","link":"https://www.bigganchinta.com/events/%E0%A6%B0%E0%A6%95%E0%A6%AE%E0%A6%BE%E0%A6%B0%E0%A6%BF-%E0%A6%AC%E0%A6%BF%E0%A6%9C%E0%A7%8D%E0%A6%9E%E0%A6%BE%E0%A6%A8%E0%A6%9A%E0%A6%BF%E0%A6%A8%E0%A7%8D%E0%A6%A4%E0%A6%BE-%E0%A6%95%E0%A7%81%E0%A6%87%E0%A6%9C-%E0%A6%86%E0%A6%B8%E0%A6%9B%E0%A7%87-%E0%A6%AC%E0%A6%BF%E0%A6%9C%E0%A7%8D%E0%A6%9E%E0%A6%BE%E0%A6%A8%E0%A6%9A%E0%A6%BF%E0%A6%A8%E0%A7%8D%E0%A6%A4%E0%A6%BE%E0%A6%B0-%E0%A6%85%E0%A6%95%E0%A7%8D%E0%A6%9F%E0%A7%8B%E0%A6%AC%E0%A6%B0-%E0%A6%B8%E0%A6%82%E0%A6%96%E0%A7%8D%E0%A6%AF%E0%A6%BE%E0%A7%9F","source_name":"Prthom Alo","news_language":"Bangla"},{"name":"কলেজে প্রথম দিন","link":"https://www.kishoralo.com/%E0%A6%95%E0%A6%B2%E0%A7%87%E0%A6%9C%E0%A7%87-%E0%A6%AA%E0%A7%8D%E0%A6%B0%E0%A6%A5%E0%A6%AE-%E0%A6%A6%E0%A6%BF%E0%A6%A8","source_name":"Prthom Alo","news_language":"Bangla"},{"name":"মেয়েদের ক্যারিয়ার-বিষয়ক ওয়েবসাইট উদ্বোধন","link":"https://www.prothomalo.com/business/corporate/%E0%A6%AE%E0%A7%87%E0%A7%9F%E0%A7%87%E0%A6%A6%E0%A7%87%E0%A6%B0-%E0%A6%95%E0%A7%8D%E0%A6%AF%E0%A6%BE%E0%A6%B0%E0%A6%BF%E0%A7%9F%E0%A6%BE%E0%A6%B0-%E0%A6%AC%E0%A6%BF%E0%A6%B7%E0%A7%9F%E0%A6%95-%E0%A6%93%E0%A7%9F%E0%A7%87%E0%A6%AC%E0%A6%B8%E0%A6%BE%E0%A6%87%E0%A6%9F-%E0%A6%89%E0%A6%A6%E0%A7%8D%E0%A6%AC%E0%A7%8B%E0%A6%A7%E0%A6%A8","source_name":"Prthom Alo","news_language":"Bangla"},{"name":"চীনের বিদ্যুত সমস্যায় ‘মরার ওপর খাঁড়ার ঘা’ ","link":"https://www.prothomalo.com/business/world-business/%E0%A6%9A%E0%A7%80%E0%A6%A8%E0%A7%87%E0%A6%B0-%E0%A6%AC%E0%A6%BF%E0%A6%A6%E0%A7%8D%E0%A6%AF%E0%A7%81%E0%A6%A4-%E0%A6%B8%E0%A6%AE%E0%A6%B8%E0%A7%8D%E0%A6%AF%E0%A6%BE%E0%A7%9F-%E0%A6%AE%E0%A6%B0%E0%A6%BE%E0%A6%B0-%E0%A6%93%E0%A6%AA%E0%A6%B0-%E0%A6%96%E0%A6%BE%E0%A6%81%E0%A7%9C%E0%A6%BE%E0%A6%B0-%E0%A6%98%E0%A6%BE","source_name":"Prthom Alo","news_language":"Bangla"},{"name":false,"link":"https://www.prothomalo.com/bangladesh/capital/%E0%A6%A2%E0%A6%BE%E0%A6%95%E0%A6%BE%E0%A7%9F-%E0%A6%8F%E0%A6%87%E0%A6%9A%E0%A6%8F%E0%A6%B8%E0%A6%B8%E0%A6%BF-%E0%A6%AA%E0%A6%B0%E0%A7%80%E0%A6%95%E0%A7%8D%E0%A6%B7%E0%A6%BE%E0%A6%B0%E0%A7%8D%E0%A6%A5%E0%A7%80-%E0%A6%A6%E0%A6%97%E0%A7%8D%E0%A6%A7-%E0%A6%88%E0%A6%B6%E0%A6%BF%E0%A6%A4%E0%A6%BE%E0%A6%B0-%E0%A6%AE%E0%A7%83%E0%A6%A4%E0%A7%8D%E0%A6%AF%E0%A7%81","source_name":"Prthom Alo","news_language":"Bangla"},{"name":"সাকিবদের কাছে হেরে গালি খাচ্ছেন কোহলি-ম্যাক্সওয়েলরা","link":"https://www.prothomalo.com/sports/cricket/%E0%A6%B8%E0%A6%BE%E0%A6%95%E0%A6%BF%E0%A6%AC%E0%A6%A6%E0%A7%87%E0%A6%B0-%E0%A6%95%E0%A6%BE%E0%A6%9B%E0%A7%87-%E0%A6%B9%E0%A7%87%E0%A6%B0%E0%A7%87-%E0%A6%97%E0%A6%BE%E0%A6%B2%E0%A6%BF-%E0%A6%96%E0%A6%BE%E0%A6%9A%E0%A7%8D%E0%A6%9B%E0%A7%87%E0%A6%A8-%E0%A6%95%E0%A7%8B%E0%A6%B9%E0%A6%B2%E0%A6%BF-%E0%A6%AE%E0%A7%8D%E0%A6%AF%E0%A6%BE%E0%A6%95%E0%A7%8D%E0%A6%B8%E0%A6%93%E0%A7%9F%E0%A7%87%E0%A6%B2%E0%A6%B0%E0%A6%BE","source_name":"Prthom Alo","news_language":"Bangla"},{"name":"এক ঝলক ( ১২ অক্টোবর, ২০২১)","link":"https://www.prothomalo.com/photo/glimpse/%E0%A6%8F%E0%A6%95-%E0%A6%9D%E0%A6%B2%E0%A6%95-%E0%A7%A7%E0%A7%A8-%E0%A6%85%E0%A6%95%E0%A7%8D%E0%A6%9F%E0%A7%8B%E0%A6%AC%E0%A6%B0-%E0%A7%A8%E0%A7%A6%E0%A7%A8%E0%A7%A7","source_name":"Prthom Alo","news_language":"Bangla"},{"name":"১৯ দিনেও সন্ধান মেলেনি অভিযুক্ত কর্মকর্তার","link":"https://www.prothomalo.com/bangladesh/district/%E0%A7%A7%E0%A7%AF-%E0%A6%A6%E0%A6%BF%E0%A6%A8%E0%A7%87%E0%A6%93-%E0%A6%B8%E0%A6%A8%E0%A7%8D%E0%A6%A7%E0%A6%BE%E0%A6%A8-%E0%A6%AE%E0%A7%87%E0%A6%B2%E0%A7%87%E0%A6%A8%E0%A6%BF-%E0%A6%85%E0%A6%AD%E0%A6%BF%E0%A6%AF%E0%A7%81%E0%A6%95%E0%A7%8D%E0%A6%A4-%E0%A6%95%E0%A6%B0%E0%A7%8D%E0%A6%AE%E0%A6%95%E0%A6%B0%E0%A7%8D%E0%A6%A4%E0%A6%BE%E0%A6%B0","source_name":"Prthom Alo","news_language":"Bangla"},{"name":"জনস্বাস্থ্য প্রকৌশল অধিদপ্তরে চাকরি, পদ ৫০","link":"https://www.prothomalo.com/chakri/employment/%E0%A6%9C%E0%A6%A8%E0%A6%B8%E0%A7%8D%E0%A6%AC%E0%A6%BE%E0%A6%B8%E0%A7%8D%E0%A6%A5%E0%A7%8D%E0%A6%AF-%E0%A6%AA%E0%A7%8D%E0%A6%B0%E0%A6%95%E0%A7%8C%E0%A6%B6%E0%A6%B2-%E0%A6%85%E0%A6%A7%E0%A6%BF%E0%A6%A6%E0%A6%AA%E0%A7%8D%E0%A6%A4%E0%A6%B0%E0%A7%87-%E0%A6%9A%E0%A6%BE%E0%A6%95%E0%A6%B0%E0%A6%BF-%E0%A6%AA%E0%A6%A6-%E0%A7%AB%E0%A7%A6","source_name":"Prthom Alo","news_language":"Bangla"},{"name":"ইলিশ নিধনে বেপরোয়া জেলেরা  ","link":"https://www.prothomalo.com/bangladesh/district/%E0%A6%87%E0%A6%B2%E0%A6%BF%E0%A6%B6-%E0%A6%A8%E0%A6%BF%E0%A6%A7%E0%A6%A8%E0%A7%87-%E0%A6%AC%E0%A7%87%E0%A6%AA%E0%A6%B0%E0%A7%8B%E0%A7%9F%E0%A6%BE-%E0%A6%9C%E0%A7%87%E0%A6%B2%E0%A7%87%E0%A6%B0%E0%A6%BE","source_name":"Prthom Alo","news_language":"Bangla"},{"name":"ভেঙে পড়ল রাজশাহী ওয়ার্কার্স পার্টির কার্যালয়ের একাংশ","link":"https://www.prothomalo.com/bangladesh/district/%E0%A6%AD%E0%A7%87%E0%A6%99%E0%A7%87-%E0%A6%AA%E0%A7%9C%E0%A6%B2-%E0%A6%B0%E0%A6%BE%E0%A6%9C%E0%A6%B6%E0%A6%BE%E0%A6%B9%E0%A7%80-%E0%A6%93%E0%A7%9F%E0%A6%BE%E0%A6%B0%E0%A7%8D%E0%A6%95%E0%A6%BE%E0%A6%B0%E0%A7%8D%E0%A6%B8-%E0%A6%AA%E0%A6%BE%E0%A6%B0%E0%A7%8D%E0%A6%9F%E0%A6%BF%E0%A6%B0-%E0%A6%95%E0%A6%BE%E0%A6%B0%E0%A7%8D%E0%A6%AF%E0%A6%BE%E0%A6%B2%E0%A7%9F%E0%A7%87%E0%A6%B0-%E0%A6%8F%E0%A6%95%E0%A6%BE%E0%A6%82%E0%A6%B6","source_name":"Prthom Alo","news_language":"Bangla"},{"name":"শারদ উৎসবে মিমের সাজ","link":"https://www.prothomalo.com/feature/naksha/%E0%A6%B6%E0%A6%BE%E0%A6%B0%E0%A6%A6-%E0%A6%89%E0%A7%8E%E0%A6%B8%E0%A6%AC%E0%A7%87-%E0%A6%AE%E0%A6%BF%E0%A6%AE%E0%A7%87%E0%A6%B0-%E0%A6%B8%E0%A6%BE%E0%A6%9C","source_name":"Prthom Alo","news_language":"Bangla"},{"name":"পদে না থেকেও মিলেছে আ.লীগের মনোনয়ন","link":"https://www.prothomalo.com/bangladesh/district/%E0%A6%AA%E0%A6%A6%E0%A7%87-%E0%A6%A8%E0%A6%BE-%E0%A6%A5%E0%A7%87%E0%A6%95%E0%A7%87%E0%A6%93-%E0%A6%AE%E0%A6%BF%E0%A6%B2%E0%A7%87%E0%A6%9B%E0%A7%87-%E0%A6%86%E0%A6%B2%E0%A7%80%E0%A6%97%E0%A7%87%E0%A6%B0-%E0%A6%AE%E0%A6%A8%E0%A7%8B%E0%A6%A8%E0%A7%9F%E0%A6%A8","source_name":"Prthom Alo","news_language":"Bangla"}]