[{"name":"ইন্টারনেটের গতি ফোর–জির চেয়ে \nকয়েক গুণ বাড়বে ফাইভ–জিতে ","link":"https://www.prothomalo.com/business/industry/%E0%A6%87%E0%A6%A8%E0%A7%8D%E0%A6%9F%E0%A6%BE%E0%A6%B0%E0%A6%A8%E0%A7%87%E0%A6%9F%E0%A7%87%E0%A6%B0-%E0%A6%97%E0%A6%A4%E0%A6%BF-%E0%A6%AB%E0%A7%8B%E0%A6%B0%E0%A6%9C%E0%A6%BF%E0%A6%B0-%E0%A6%9A%E0%A7%87%E0%A7%9F%E0%A7%87-%E0%A6%95%E0%A7%9F%E0%A7%87%E0%A6%95-%E0%A6%97%E0%A7%81%E0%A6%A3-%E0%A6%AC%E0%A6%BE%E0%A7%9C%E0%A6%AC%E0%A7%87-%E0%A6%AB%E0%A6%BE%E0%A6%87%E0%A6%AD%E0%A6%9C%E0%A6%BF%E0%A6%A4%E0%A7%87","source_name":"Prthom Alo","news_language":"Bangla"},{"name":"আলোকচিত্রী শহিদুলের মামলার তদন্ত চলবে","link":"https://www.prothomalo.com/bangladesh/capital/%E0%A6%86%E0%A6%B2%E0%A7%8B%E0%A6%95%E0%A6%9A%E0%A6%BF%E0%A6%A4%E0%A7%8D%E0%A6%B0%E0%A7%80-%E0%A6%B6%E0%A6%B9%E0%A6%BF%E0%A6%A6%E0%A7%81%E0%A6%B2%E0%A7%87%E0%A6%B0-%E0%A6%AE%E0%A6%BE%E0%A6%AE%E0%A6%B2%E0%A6%BE%E0%A6%B0-%E0%A6%A4%E0%A6%A6%E0%A6%A8%E0%A7%8D%E0%A6%A4-%E0%A6%9A%E0%A6%B2%E0%A6%AC%E0%A7%87","source_name":"Prthom Alo","news_language":"Bangla"},{"name":"টেকসই পোশাকশিল্পের জন্য যা দরকার","link":"https://www.prothomalo.com/business/industry/%E0%A6%9F%E0%A7%87%E0%A6%95%E0%A6%B8%E0%A6%87-%E0%A6%AA%E0%A7%8B%E0%A6%B6%E0%A6%BE%E0%A6%95%E0%A6%B6%E0%A6%BF%E0%A6%B2%E0%A7%8D%E0%A6%AA%E0%A7%87%E0%A6%B0-%E0%A6%9C%E0%A6%A8%E0%A7%8D%E0%A6%AF-%E0%A6%AF%E0%A6%BE-%E0%A6%A6%E0%A6%B0%E0%A6%95%E0%A6%BE%E0%A6%B0","source_name":"Prthom Alo","news_language":"Bangla"},{"name":"অমিক্রন নিয়ে সতর্ক থাকার নির্দেশ প্রধানমন্ত্রীর","link":"https://www.prothomalo.com/bangladesh/%E0%A6%85%E0%A6%AE%E0%A6%BF%E0%A6%95%E0%A7%8D%E0%A6%B0%E0%A6%A8-%E0%A6%A8%E0%A6%BF%E0%A7%9F%E0%A7%87-%E0%A6%B8%E0%A6%A4%E0%A6%B0%E0%A7%8D%E0%A6%95-%E0%A6%A5%E0%A6%BE%E0%A6%95%E0%A6%BE%E0%A6%B0-%E0%A6%A8%E0%A6%BF%E0%A6%B0%E0%A7%8D%E0%A6%A6%E0%A7%87%E0%A6%B6-%E0%A6%AA%E0%A7%8D%E0%A6%B0%E0%A6%A7%E0%A6%BE%E0%A6%A8%E0%A6%AE%E0%A6%A8%E0%A7%8D%E0%A6%A4%E0%A7%8D%E0%A6%B0%E0%A7%80%E0%A6%B0","source_name":"Prthom Alo","news_language":"Bangla"},{"name":false,"link":"https://www.prothomalo.com/bangladesh/district/%E0%A6%A8%E0%A7%8B%E0%A7%9F%E0%A6%BE%E0%A6%96%E0%A6%BE%E0%A6%B2%E0%A7%80%E0%A6%A4%E0%A7%87-%E0%A6%A8%E0%A6%BF%E0%A6%B0%E0%A7%8D%E0%A6%AC%E0%A6%BE%E0%A6%9A%E0%A6%A8%E0%A7%80-%E0%A6%95%E0%A7%8D%E0%A6%AF%E0%A6%BE%E0%A6%AE%E0%A7%8D%E0%A6%AA-%E0%A6%93-%E0%A6%AC%E0%A6%B8%E0%A6%A4%E0%A6%98%E0%A6%B0%E0%A7%87-%E0%A6%AA%E0%A6%BE%E0%A6%B2%E0%A7%8D%E0%A6%9F%E0%A6%BE%E0%A6%AA%E0%A6%BE%E0%A6%B2%E0%A7%8D%E0%A6%9F%E0%A6%BF-%E0%A6%B9%E0%A6%BE%E0%A6%AE%E0%A6%B2%E0%A6%BE-%E0%A6%86%E0%A6%B9%E0%A6%A4-%E0%A7%AB","source_name":"Prthom Alo","news_language":"Bangla"},{"name":"নির্বাচনী প্রচারে আরব সাগর তীরের রাজ্যে মমতা","link":"https://www.prothomalo.com/world/india/%E0%A6%A8%E0%A6%BF%E0%A6%B0%E0%A7%8D%E0%A6%AC%E0%A6%BE%E0%A6%9A%E0%A6%A8%E0%A7%80-%E0%A6%AA%E0%A7%8D%E0%A6%B0%E0%A6%9A%E0%A6%BE%E0%A6%B0%E0%A7%87-%E0%A6%86%E0%A6%B0%E0%A6%AC-%E0%A6%B8%E0%A6%BE%E0%A6%97%E0%A6%B0-%E0%A6%A4%E0%A7%80%E0%A6%B0%E0%A7%87%E0%A6%B0-%E0%A6%B0%E0%A6%BE%E0%A6%9C%E0%A7%8D%E0%A6%AF%E0%A7%87-%E0%A6%AE%E0%A6%AE%E0%A6%A4%E0%A6%BE","source_name":"Prthom Alo","news_language":"Bangla"},{"name":"দক্ষিণ কোরিয়ায় করোনা রোগীদের গতিবিধি অনুসরণ করবে কৃত্রিম বুদ্ধিমত্তা ","link":"https://www.prothomalo.com/world/asia/%E0%A6%A6%E0%A6%95%E0%A7%8D%E0%A6%B7%E0%A6%BF%E0%A6%A3-%E0%A6%95%E0%A7%8B%E0%A6%B0%E0%A6%BF%E0%A7%9F%E0%A6%BE%E0%A7%9F-%E0%A6%95%E0%A6%B0%E0%A7%8B%E0%A6%A8%E0%A6%BE-%E0%A6%B0%E0%A7%8B%E0%A6%97%E0%A7%80%E0%A6%A6%E0%A7%87%E0%A6%B0-%E0%A6%97%E0%A6%A4%E0%A6%BF%E0%A6%AC%E0%A6%BF%E0%A6%A7%E0%A6%BF-%E0%A6%85%E0%A6%A8%E0%A7%81%E0%A6%B8%E0%A6%B0%E0%A6%A3-%E0%A6%95%E0%A6%B0%E0%A6%AC%E0%A7%87-%E0%A6%95%E0%A7%83%E0%A6%A4%E0%A7%8D%E0%A6%B0%E0%A6%BF%E0%A6%AE-%E0%A6%AC%E0%A7%81%E0%A6%A6%E0%A7%8D%E0%A6%A7%E0%A6%BF%E0%A6%AE%E0%A6%A4%E0%A7%8D%E0%A6%A4%E0%A6%BE","source_name":"Prthom Alo","news_language":"Bangla"},{"name":"লাবিবা-লামিসাকে এখনই আলাদা করা সম্ভব নয়: চিকিৎসক","link":"https://www.prothomalo.com/bangladesh/capital/%E0%A6%B2%E0%A6%BE%E0%A6%AC%E0%A6%BF%E0%A6%AC%E0%A6%BE-%E0%A6%B2%E0%A6%BE%E0%A6%AE%E0%A6%BF%E0%A6%B8%E0%A6%BE%E0%A6%95%E0%A7%87-%E0%A6%8F%E0%A6%96%E0%A6%A8%E0%A6%87-%E0%A6%86%E0%A6%B2%E0%A6%BE%E0%A6%A6%E0%A6%BE-%E0%A6%95%E0%A6%B0%E0%A6%BE-%E0%A6%B8%E0%A6%AE%E0%A7%8D%E0%A6%AD%E0%A6%AC-%E0%A6%A8%E0%A7%9F-%E0%A6%9A%E0%A6%BF%E0%A6%95%E0%A6%BF%E0%A7%8E%E0%A6%B8%E0%A6%95","source_name":"Prthom Alo","news_language":"Bangla"},{"name":"ফোটনের কি বুদ্ধি আছে?","link":"https://www.bigganchinta.com/physics/does-the-photon-have-intelligence","source_name":"Prthom Alo","news_language":"Bangla"},{"name":"বিশ্বসুন্দরী হওয়ার স্বপ্নপূরণ","link":"https://www.prothomalo.com/entertainment/bollywood/%E0%A6%AC%E0%A6%BF%E0%A6%B6%E0%A7%8D%E0%A6%AC%E0%A6%B8%E0%A7%81%E0%A6%A8%E0%A7%8D%E0%A6%A6%E0%A6%B0%E0%A7%80-%E0%A6%B9%E0%A6%93%E0%A7%9F%E0%A6%BE%E0%A6%B0-%E0%A6%B8%E0%A7%8D%E0%A6%AC%E0%A6%AA%E0%A7%8D%E0%A6%A8%E0%A6%AA%E0%A7%82%E0%A6%B0%E0%A6%A3","source_name":"Prthom Alo","news_language":"Bangla"},{"name":"সবচেয়ে নিচের ধাপে নামিয়ে দেওয়ার অপমানে খেলবেনই না কামরান আকমল","link":"https://www.prothomalo.com/sports/cricket/%E0%A6%B8%E0%A6%AC%E0%A6%9A%E0%A7%87%E0%A7%9F%E0%A7%87-%E0%A6%A8%E0%A6%BF%E0%A6%9A%E0%A7%87%E0%A6%B0-%E0%A6%A7%E0%A6%BE%E0%A6%AA%E0%A7%87-%E0%A6%A8%E0%A6%BE%E0%A6%AE%E0%A6%BF%E0%A7%9F%E0%A7%87-%E0%A6%A6%E0%A7%87%E0%A6%93%E0%A7%9F%E0%A6%BE%E0%A6%B0-%E0%A6%85%E0%A6%AA%E0%A6%AE%E0%A6%BE%E0%A6%A8%E0%A7%87-%E0%A6%96%E0%A7%87%E0%A6%B2%E0%A6%AC%E0%A7%87%E0%A6%A8%E0%A6%87-%E0%A6%A8%E0%A6%BE-%E0%A6%95%E0%A6%BE%E0%A6%AE%E0%A6%B0%E0%A6%BE%E0%A6%A8-%E0%A6%86%E0%A6%95%E0%A6%AE%E0%A6%B2","source_name":"Prthom Alo","news_language":"Bangla"},{"name":"মুরাদ হাসানের নামে আদালতে মামলার আবেদন, আদেশের জন্য অপেক্ষা","link":"https://www.prothomalo.com/bangladesh/district/%E0%A6%AE%E0%A7%81%E0%A6%B0%E0%A6%BE%E0%A6%A6-%E0%A6%B9%E0%A6%BE%E0%A6%B8%E0%A6%BE%E0%A6%A8%E0%A7%87%E0%A6%B0-%E0%A6%A8%E0%A6%BE%E0%A6%AE%E0%A7%87-%E0%A6%86%E0%A6%A6%E0%A6%BE%E0%A6%B2%E0%A6%A4%E0%A7%87-%E0%A6%AE%E0%A6%BE%E0%A6%AE%E0%A6%B2%E0%A6%BE%E0%A6%B0-%E0%A6%86%E0%A6%AC%E0%A7%87%E0%A6%A6%E0%A6%A8-%E0%A6%86%E0%A6%A6%E0%A7%87%E0%A6%B6%E0%A7%87%E0%A6%B0-%E0%A6%9C%E0%A6%A8%E0%A7%8D%E0%A6%AF-%E0%A6%85%E0%A6%AA%E0%A7%87%E0%A6%95%E0%A7%8D%E0%A6%B7%E0%A6%BE","source_name":"Prthom Alo","news_language":"Bangla"},{"name":"রক্তে আঁকা ভোর: বিশ্বস্ত কল্পনায় মুক্তিযুদ্ধের বয়ান","link":"https://www.prothomalo.com/onnoalo/%E0%A6%B0%E0%A6%95%E0%A7%8D%E0%A6%A4%E0%A7%87-%E0%A6%86%E0%A6%81%E0%A6%95%E0%A6%BE-%E0%A6%AD%E0%A7%8B%E0%A6%B0-%E0%A6%AC%E0%A6%BF%E0%A6%B6%E0%A7%8D%E0%A6%AC%E0%A6%B8%E0%A7%8D%E0%A6%A4-%E0%A6%95%E0%A6%B2%E0%A7%8D%E0%A6%AA%E0%A6%A8%E0%A6%BE%E0%A7%9F-%E0%A6%AE%E0%A7%81%E0%A6%95%E0%A7%8D%E0%A6%A4%E0%A6%BF%E0%A6%AF%E0%A7%81%E0%A6%A6%E0%A7%8D%E0%A6%A7%E0%A7%87%E0%A6%B0-%E0%A6%AC%E0%A7%9F%E0%A6%BE%E0%A6%A8","source_name":"Prthom Alo","news_language":"Bangla"},{"name":"কসমিক হ্যাকার ","link":"https://www.bigganchinta.com/sciencefiction/cosmic-hacker","source_name":"Prthom Alo","news_language":"Bangla"},{"name":"শিবচরে নছিমন উল্টে প্রাণ গেল দুই নির্মাণশ্রমি‌কের","link":"https://www.prothomalo.com/bangladesh/district/%E0%A6%B6%E0%A6%BF%E0%A6%AC%E0%A6%9A%E0%A6%B0%E0%A7%87-%E0%A6%A8%E0%A6%9B%E0%A6%BF%E0%A6%AE%E0%A6%A8-%E0%A6%89%E0%A6%B2%E0%A7%8D%E0%A6%9F%E0%A7%87-%E0%A6%AA%E0%A7%8D%E0%A6%B0%E0%A6%BE%E0%A6%A3-%E0%A6%97%E0%A7%87%E0%A6%B2-%E0%A6%A6%E0%A7%81%E0%A6%87-%E0%A6%A8%E0%A6%BF%E0%A6%B0%E0%A7%8D%E0%A6%AE%E0%A6%BE%E0%A6%A3%E0%A6%B6%E0%A7%8D%E0%A6%B0%E0%A6%AE%E0%A6%BF%E0%A6%95%E0%A7%87%E0%A6%B0","source_name":"Prthom Alo","news_language":"Bangla"},{"name":false,"link":"https://www.prothomalo.com/bangladesh/district/%E0%A6%A6%E0%A6%B0%E0%A6%9C%E0%A6%BE-%E0%A6%96%E0%A7%81%E0%A6%B2%E0%A6%A4%E0%A7%87%E0%A6%87-%E0%A6%A8%E0%A6%BE%E0%A6%B0%E0%A7%80%E0%A6%95%E0%A7%87-%E0%A6%8F%E0%A6%B2%E0%A7%8B%E0%A6%AA%E0%A6%BE%E0%A6%A4%E0%A6%BE%E0%A7%9C%E0%A6%BF-%E0%A6%95%E0%A7%81%E0%A6%AA%E0%A6%BF%E0%A7%9F%E0%A7%87-%E0%A6%B9%E0%A6%A4%E0%A7%8D%E0%A6%AF%E0%A6%BE-%E0%A6%86%E0%A6%B9%E0%A6%A4-%E0%A6%AC%E0%A7%8B%E0%A6%A8-%E0%A6%A6%E0%A7%81%E0%A6%B2%E0%A6%BE%E0%A6%AD%E0%A6%BE%E0%A6%87","source_name":"Prthom Alo","news_language":"Bangla"}]